[{"data": "2012/01/03", "OPENPRC": "44.69", "PRC": "43.76", "BIDLO": "43.44", "ASKHI": "44.93"}, {"data": "2012/01/04", "OPENPRC": "43.71", "PRC": "44.36", "BIDLO": "43.25", "ASKHI": "44.41"}, {"data": "2012/01/05", "OPENPRC": "44.3", "PRC": "45.13", "BIDLO": "43.82", "ASKHI": "45.16"}, {"data": "2012/01/06", "OPENPRC": "45.19", "PRC": "45.21", "BIDLO": "44.77", "ASKHI": "45.44"}, {"data": "2012/01/09", "OPENPRC": "45.25", "PRC": "45.17", "BIDLO": "44.9", "ASKHI": "45.42"}, {"data": "2012/01/10", "OPENPRC": "45.51", "PRC": "45.01", "BIDLO": "44.43", "ASKHI": "45.8119"}, {"data": "2012/01/11", "OPENPRC": "45.01", "PRC": "45.22", "BIDLO": "44.75", "ASKHI": "45.41"}, {"data": "2012/01/12", "OPENPRC": "45.4", "PRC": "45.86", "BIDLO": "45.28", "ASKHI": "46.09"}, {"data": "2012/01/13", "OPENPRC": "45.65", "PRC": "46.59", "BIDLO": "45.39", "ASKHI": "46.66"}, {"data": "2012/01/17", "OPENPRC": "47.25", "PRC": "46.79", "BIDLO": "46.54", "ASKHI": "47.59"}, {"data": "2012/01/18", "OPENPRC": "45.4", "PRC": "45.53", "BIDLO": "44.79", "ASKHI": "46.11"}, {"data": "2012/01/19", "OPENPRC": "45.8", "PRC": "45.74", "BIDLO": "45.39", "ASKHI": "45.99"}, {"data": "2012/01/20", "OPENPRC": "45.61", "PRC": "45.86", "BIDLO": "45.38", "ASKHI": "45.98"}, {"data": "2012/01/23", "OPENPRC": "45.87", "PRC": "46.07", "BIDLO": "45.81", "ASKHI": "46.985"}, {"data": "2012/01/24", "OPENPRC": "46.08", "PRC": "46.86", "BIDLO": "45.81", "ASKHI": "46.87"}, {"data": "2012/01/25", "OPENPRC": "46.74", "PRC": "46.74", "BIDLO": "46.02", "ASKHI": "46.87"}, {"data": "2012/01/26", "OPENPRC": "47.12", "PRC": "46.78", "BIDLO": "46.53", "ASKHI": "47.18"}, {"data": "2012/01/27", "OPENPRC": "46.66", "PRC": "46.69", "BIDLO": "46.355", "ASKHI": "46.96"}, {"data": "2012/01/30", "OPENPRC": "46.18", "PRC": "46.63", "BIDLO": "45.8686", "ASKHI": "46.83"}, {"data": "2012/01/31", "OPENPRC": "46.89", "PRC": "46.68", "BIDLO": "46.48", "ASKHI": "47.07"}, {"data": "2012/02/01", "OPENPRC": "47.21", "PRC": "47.07", "BIDLO": "47.0", "ASKHI": "47.4"}, {"data": "2012/02/02", "OPENPRC": "47.16", "PRC": "46.97", "BIDLO": "46.85", "ASKHI": "47.39"}, {"data": "2012/02/03", "OPENPRC": "47.61", "PRC": "48.3", "BIDLO": "47.46", "ASKHI": "48.32"}, {"data": "2012/02/06", "OPENPRC": "48.24", "PRC": "48.06", "BIDLO": "47.84", "ASKHI": "48.56"}, {"data": "2012/02/07", "OPENPRC": "47.82", "PRC": "48.08", "BIDLO": "47.42", "ASKHI": "48.2999"}, {"data": "2012/02/08", "OPENPRC": "48.13", "PRC": "48.83", "BIDLO": "47.87", "ASKHI": "48.87"}, {"data": "2012/02/09", "OPENPRC": "48.9", "PRC": "48.21", "BIDLO": "47.81", "ASKHI": "48.96"}, {"data": "2012/02/10", "OPENPRC": "47.92", "PRC": "48.42", "BIDLO": "47.59", "ASKHI": "48.47"}, {"data": "2012/02/13", "OPENPRC": "48.95", "PRC": "50.58", "BIDLO": "48.86", "ASKHI": "50.63"}, {"data": "2012/02/14", "OPENPRC": "50.53", "PRC": "51.24", "BIDLO": "50.5", "ASKHI": "51.58"}, {"data": "2012/02/15", "OPENPRC": "51.57", "PRC": "50.63", "BIDLO": "50.51", "ASKHI": "51.6"}, {"data": "2012/02/16", "OPENPRC": "50.63", "PRC": "50.82", "BIDLO": "50.6", "ASKHI": "51.37"}, {"data": "2012/02/17", "OPENPRC": "50.81", "PRC": "50.73", "BIDLO": "50.54", "ASKHI": "51.15"}, {"data": "2012/02/21", "OPENPRC": "50.85", "PRC": "50.845", "BIDLO": "50.35", "ASKHI": "51.06"}, {"data": "2012/02/22", "OPENPRC": "50.92", "PRC": "51.29", "BIDLO": "50.69", "ASKHI": "51.32"}, {"data": "2012/02/23", "OPENPRC": "51.09", "PRC": "51.93", "BIDLO": "51.09", "ASKHI": "51.97"}, {"data": "2012/02/24", "OPENPRC": "52.1", "PRC": "51.97", "BIDLO": "51.92", "ASKHI": "52.25"}, {"data": "2012/02/27", "OPENPRC": "51.93", "PRC": "52.43", "BIDLO": "51.9", "ASKHI": "52.786"}, {"data": "2012/02/28", "OPENPRC": "52.62", "PRC": "52.34", "BIDLO": "52.13", "ASKHI": "52.65"}, {"data": "2012/02/29", "OPENPRC": "52.41", "PRC": "52.68", "BIDLO": "52.17", "ASKHI": "52.82"}, {"data": "2012/03/01", "OPENPRC": "52.91", "PRC": "52.93", "BIDLO": "52.36", "ASKHI": "53.01"}, {"data": "2012/03/02", "OPENPRC": "52.91", "PRC": "53.1", "BIDLO": "52.625", "ASKHI": "53.15"}, {"data": "2012/03/05", "OPENPRC": "53.13", "PRC": "53.35", "BIDLO": "52.88", "ASKHI": "53.56"}, {"data": "2012/03/06", "OPENPRC": "52.98", "PRC": "52.17", "BIDLO": "51.81", "ASKHI": "53.09"}, {"data": "2012/03/07", "OPENPRC": "52.21", "PRC": "52.75", "BIDLO": "52.08", "ASKHI": "52.9099"}, {"data": "2012/03/08", "OPENPRC": "53.21", "PRC": "52.78", "BIDLO": "52.65", "ASKHI": "53.34"}, {"data": "2012/03/09", "OPENPRC": "52.97", "PRC": "52.88", "BIDLO": "52.44", "ASKHI": "53.15"}, {"data": "2012/03/12", "OPENPRC": "52.99", "PRC": "52.83", "BIDLO": "52.75", "ASKHI": "53.1"}, {"data": "2012/03/13", "OPENPRC": "53.0", "PRC": "53.29", "BIDLO": "52.47", "ASKHI": "53.33"}, {"data": "2012/03/14", "OPENPRC": "53.43", "PRC": "52.83", "BIDLO": "52.52", "ASKHI": "53.6"}, {"data": "2012/03/15", "OPENPRC": "52.83", "PRC": "52.55", "BIDLO": "51.97", "ASKHI": "52.9"}, {"data": "2012/03/16", "OPENPRC": "52.42", "PRC": "52.22", "BIDLO": "52.14", "ASKHI": "52.75"}, {"data": "2012/03/19", "OPENPRC": "52.05", "PRC": "52.01", "BIDLO": "51.53", "ASKHI": "52.14"}, {"data": "2012/03/20", "OPENPRC": "51.84", "PRC": "52.86", "BIDLO": "51.38", "ASKHI": "53.009"}, {"data": "2012/03/21", "OPENPRC": "52.86", "PRC": "53.93", "BIDLO": "52.86", "ASKHI": "54.24"}, {"data": "2012/03/22", "OPENPRC": "53.71", "PRC": "53.71", "BIDLO": "53.24", "ASKHI": "53.98"}, {"data": "2012/03/23", "OPENPRC": "53.77", "PRC": "53.64", "BIDLO": "53.15", "ASKHI": "53.95"}, {"data": "2012/03/26", "OPENPRC": "54.07", "PRC": "54.57", "BIDLO": "54.07", "ASKHI": "54.72"}, {"data": "2012/03/27", "OPENPRC": "54.71", "PRC": "54.59", "BIDLO": "54.48", "ASKHI": "55.05"}, {"data": "2012/03/28", "OPENPRC": "54.54", "PRC": "54.19", "BIDLO": "53.6", "ASKHI": "54.65"}, {"data": "2012/03/29", "OPENPRC": "54.03", "PRC": "54.26", "BIDLO": "53.6", "ASKHI": "54.31"}, {"data": "2012/03/30", "OPENPRC": "54.71", "PRC": "54.1", "BIDLO": "53.91", "ASKHI": "54.72"}, {"data": "2012/04/02", "OPENPRC": "54.34", "PRC": "54.65", "BIDLO": "53.82", "ASKHI": "54.8"}, {"data": "2012/04/03", "OPENPRC": "53.73", "PRC": "53.37", "BIDLO": "52.89", "ASKHI": "54.27"}, {"data": "2012/04/04", "OPENPRC": "53.21", "PRC": "52.94", "BIDLO": "52.64", "ASKHI": "53.32"}, {"data": "2012/04/05", "OPENPRC": "52.79", "PRC": "52.975", "BIDLO": "52.72", "ASKHI": "53.41"}, {"data": "2012/04/09", "OPENPRC": "52.54", "PRC": "51.58", "BIDLO": "51.51", "ASKHI": "52.58"}, {"data": "2012/04/10", "OPENPRC": "51.5", "PRC": "48.9", "BIDLO": "48.83", "ASKHI": "51.5"}, {"data": "2012/04/11", "OPENPRC": "49.55", "PRC": "49.63", "BIDLO": "49.19", "ASKHI": "50.07"}, {"data": "2012/04/12", "OPENPRC": "48.5", "PRC": "48.87", "BIDLO": "47.73", "ASKHI": "49.4697"}, {"data": "2012/04/13", "OPENPRC": "48.65", "PRC": "48.79", "BIDLO": "48.02", "ASKHI": "49.49"}, {"data": "2012/04/16", "OPENPRC": "48.91", "PRC": "48.25", "BIDLO": "48.195", "ASKHI": "49.12"}, {"data": "2012/04/17", "OPENPRC": "48.6", "PRC": "49.01", "BIDLO": "48.135", "ASKHI": "49.17"}, {"data": "2012/04/18", "OPENPRC": "48.55", "PRC": "48.49", "BIDLO": "48.25", "ASKHI": "48.79"}, {"data": "2012/04/19", "OPENPRC": "48.37", "PRC": "47.5", "BIDLO": "47.28", "ASKHI": "48.49"}, {"data": "2012/04/20", "OPENPRC": "47.89", "PRC": "48.21", "BIDLO": "47.58", "ASKHI": "48.42"}, {"data": "2012/04/23", "OPENPRC": "47.76", "PRC": "46.37", "BIDLO": "46.23", "ASKHI": "47.76"}, {"data": "2012/04/24", "OPENPRC": "46.31", "PRC": "46.29", "BIDLO": "45.61", "ASKHI": "46.58"}, {"data": "2012/04/25", "OPENPRC": "46.59", "PRC": "47.17", "BIDLO": "46.38", "ASKHI": "47.24"}, {"data": "2012/04/26", "OPENPRC": "47.12", "PRC": "47.21", "BIDLO": "46.63", "ASKHI": "47.4"}, {"data": "2012/04/27", "OPENPRC": "47.42", "PRC": "47.69", "BIDLO": "47.29", "ASKHI": "48.13"}, {"data": "2012/04/30", "OPENPRC": "47.42", "PRC": "46.82", "BIDLO": "46.72", "ASKHI": "47.65"}, {"data": "2012/05/01", "OPENPRC": "46.71", "PRC": "47.01", "BIDLO": "46.36", "ASKHI": "47.55"}, {"data": "2012/05/02", "OPENPRC": "46.58", "PRC": "47.48", "BIDLO": "46.41", "ASKHI": "47.55"}, {"data": "2012/05/03", "OPENPRC": "47.65", "PRC": "45.79", "BIDLO": "45.78", "ASKHI": "47.89"}, {"data": "2012/05/04", "OPENPRC": "45.29", "PRC": "44.29", "BIDLO": "44.11", "ASKHI": "45.62"}, {"data": "2012/05/07", "OPENPRC": "43.99", "PRC": "43.83", "BIDLO": "43.705", "ASKHI": "44.35"}, {"data": "2012/05/08", "OPENPRC": "43.43", "PRC": "43.84", "BIDLO": "42.63", "ASKHI": "44.0662"}, {"data": "2012/05/09", "OPENPRC": "43.38", "PRC": "43.14", "BIDLO": "42.94", "ASKHI": "43.52"}, {"data": "2012/05/10", "OPENPRC": "43.44", "PRC": "44.14", "BIDLO": "43.44", "ASKHI": "44.3"}, {"data": "2012/05/11", "OPENPRC": "43.8", "PRC": "43.82", "BIDLO": "43.31", "ASKHI": "44.45"}, {"data": "2012/05/14", "OPENPRC": "43.26", "PRC": "43.43", "BIDLO": "42.9401", "ASKHI": "43.76"}, {"data": "2012/05/15", "OPENPRC": "43.26", "PRC": "43.38", "BIDLO": "43.25", "ASKHI": "44.17"}, {"data": "2012/05/16", "OPENPRC": "43.68", "PRC": "43.9", "BIDLO": "43.47", "ASKHI": "44.18"}, {"data": "2012/05/17", "OPENPRC": "43.95", "PRC": "42.33", "BIDLO": "42.28", "ASKHI": "44.0"}, {"data": "2012/05/18", "OPENPRC": "42.64", "PRC": "41.86", "BIDLO": "41.72", "ASKHI": "42.83"}, {"data": "2012/05/21", "OPENPRC": "42.0", "PRC": "43.15", "BIDLO": "41.89", "ASKHI": "43.25"}, {"data": "2012/05/22", "OPENPRC": "43.5", "PRC": "44.04", "BIDLO": "43.13", "ASKHI": "44.47"}, {"data": "2012/05/23", "OPENPRC": "43.59", "PRC": "44.22", "BIDLO": "43.09", "ASKHI": "44.32"}, {"data": "2012/05/24", "OPENPRC": "44.34", "PRC": "44.36", "BIDLO": "43.75", "ASKHI": "44.48"}, {"data": "2012/05/25", "OPENPRC": "44.59", "PRC": "44.4", "BIDLO": "44.18", "ASKHI": "44.69"}, {"data": "2012/05/29", "OPENPRC": "45.035", "PRC": "45.43", "BIDLO": "44.77", "ASKHI": "45.71"}, {"data": "2012/05/30", "OPENPRC": "44.86", "PRC": "44.48", "BIDLO": "44.08", "ASKHI": "44.9499"}, {"data": "2012/05/31", "OPENPRC": "44.39", "PRC": "44.23", "BIDLO": "43.615", "ASKHI": "44.5"}, {"data": "2012/06/01", "OPENPRC": "43.45", "PRC": "43.18", "BIDLO": "43.07", "ASKHI": "43.8"}, {"data": "2012/06/04", "OPENPRC": "43.26", "PRC": "43.38", "BIDLO": "42.71", "ASKHI": "43.66"}, {"data": "2012/06/05", "OPENPRC": "41.95", "PRC": "39.15", "BIDLO": "38.81", "ASKHI": "41.96"}, {"data": "2012/06/06", "OPENPRC": "39.22", "PRC": "39.505", "BIDLO": "38.56", "ASKHI": "39.53"}, {"data": "2012/06/07", "OPENPRC": "39.88", "PRC": "39.56", "BIDLO": "39.36", "ASKHI": "40.26"}, {"data": "2012/06/08", "OPENPRC": "39.56", "PRC": "40.27", "BIDLO": "39.34", "ASKHI": "40.407"}, {"data": "2012/06/11", "OPENPRC": "40.74", "PRC": "38.98", "BIDLO": "38.92", "ASKHI": "40.86"}, {"data": "2012/06/12", "OPENPRC": "38.91", "PRC": "39.35", "BIDLO": "38.7", "ASKHI": "39.44"}, {"data": "2012/06/13", "OPENPRC": "39.14", "PRC": "38.82", "BIDLO": "38.6099", "ASKHI": "39.42"}, {"data": "2012/06/14", "OPENPRC": "38.96", "PRC": "39.03", "BIDLO": "38.59", "ASKHI": "39.3355"}, {"data": "2012/06/15", "OPENPRC": "39.32", "PRC": "39.6", "BIDLO": "39.15", "ASKHI": "39.63"}, {"data": "2012/06/18", "OPENPRC": "39.22", "PRC": "39.69", "BIDLO": "39.0", "ASKHI": "39.75"}, {"data": "2012/06/19", "OPENPRC": "39.98", "PRC": "40.46", "BIDLO": "39.97", "ASKHI": "40.74"}, {"data": "2012/06/20", "OPENPRC": "40.55", "PRC": "40.37", "BIDLO": "39.93", "ASKHI": "40.71"}, {"data": "2012/06/21", "OPENPRC": "40.55", "PRC": "38.91", "BIDLO": "38.85", "ASKHI": "40.7599"}, {"data": "2012/06/22", "OPENPRC": "39.17", "PRC": "38.92", "BIDLO": "38.58", "ASKHI": "39.19"}, {"data": "2012/06/25", "OPENPRC": "38.61", "PRC": "38.67", "BIDLO": "38.28", "ASKHI": "38.79"}, {"data": "2012/06/26", "OPENPRC": "38.81", "PRC": "38.56", "BIDLO": "38.1618", "ASKHI": "39.04"}, {"data": "2012/06/27", "OPENPRC": "38.56", "PRC": "38.37", "BIDLO": "38.13", "ASKHI": "38.86"}, {"data": "2012/06/28", "OPENPRC": "38.19", "PRC": "38.63", "BIDLO": "37.61", "ASKHI": "38.67"}, {"data": "2012/06/29", "OPENPRC": "39.26", "PRC": "40.31", "BIDLO": "39.18", "ASKHI": "40.31"}, {"data": "2012/07/02", "OPENPRC": "40.35", "PRC": "39.03", "BIDLO": "38.72", "ASKHI": "40.35"}, {"data": "2012/07/03", "OPENPRC": "39.03", "PRC": "40.8", "BIDLO": "38.83", "ASKHI": "40.81"}, {"data": "2012/07/05", "OPENPRC": "40.55", "PRC": "41.29", "BIDLO": "40.48", "ASKHI": "41.54"}, {"data": "2012/07/06", "OPENPRC": "41.17", "PRC": "40.68", "BIDLO": "40.46", "ASKHI": "41.42"}, {"data": "2012/07/09", "OPENPRC": "40.68", "PRC": "40.57", "BIDLO": "40.13", "ASKHI": "40.83"}, {"data": "2012/07/10", "OPENPRC": "40.76", "PRC": "39.81", "BIDLO": "39.56", "ASKHI": "41.06"}, {"data": "2012/07/11", "OPENPRC": "39.79", "PRC": "39.81", "BIDLO": "39.17", "ASKHI": "40.05"}, {"data": "2012/07/12", "OPENPRC": "39.77", "PRC": "42.31", "BIDLO": "39.75", "ASKHI": "42.7"}, {"data": "2012/07/13", "OPENPRC": "42.41", "PRC": "43.262", "BIDLO": "42.36", "ASKHI": "43.56"}, {"data": "2012/07/16", "OPENPRC": "43.24", "PRC": "42.99", "BIDLO": "42.48", "ASKHI": "43.67"}, {"data": "2012/07/17", "OPENPRC": "43.17", "PRC": "43.33", "BIDLO": "42.68", "ASKHI": "43.68"}, {"data": "2012/07/18", "OPENPRC": "43.208", "PRC": "44.88", "BIDLO": "43.0", "ASKHI": "44.98"}, {"data": "2012/07/19", "OPENPRC": "44.92", "PRC": "45.3", "BIDLO": "44.46", "ASKHI": "45.44"}, {"data": "2012/07/20", "OPENPRC": "45.1", "PRC": "43.96", "BIDLO": "43.93", "ASKHI": "45.13"}, {"data": "2012/07/23", "OPENPRC": "43.19", "PRC": "44.07", "BIDLO": "42.7593", "ASKHI": "44.2"}, {"data": "2012/07/24", "OPENPRC": "44.16", "PRC": "42.835", "BIDLO": "42.3418", "ASKHI": "44.17"}, {"data": "2012/07/25", "OPENPRC": "43.05", "PRC": "42.81", "BIDLO": "42.54", "ASKHI": "43.32"}, {"data": "2012/07/26", "OPENPRC": "43.67", "PRC": "43.465", "BIDLO": "43.11", "ASKHI": "44.343"}, {"data": "2012/07/27", "OPENPRC": "43.91", "PRC": "44.21", "BIDLO": "43.61", "ASKHI": "44.61"}, {"data": "2012/07/30", "OPENPRC": "44.23", "PRC": "43.81", "BIDLO": "43.72", "ASKHI": "44.53"}, {"data": "2012/07/31", "OPENPRC": "43.79", "PRC": "43.12", "BIDLO": "43.07", "ASKHI": "43.96"}, {"data": "2012/08/01", "OPENPRC": "43.44", "PRC": "42.22", "BIDLO": "42.06", "ASKHI": "43.62"}, {"data": "2012/08/02", "OPENPRC": "41.71", "PRC": "42.47", "BIDLO": "41.48", "ASKHI": "42.87"}, {"data": "2012/08/03", "OPENPRC": "43.09", "PRC": "43.09", "BIDLO": "42.66", "ASKHI": "43.31"}, {"data": "2012/08/06", "OPENPRC": "43.03", "PRC": "42.72", "BIDLO": "42.58", "ASKHI": "43.19"}, {"data": "2012/08/07", "OPENPRC": "43.0", "PRC": "43.54", "BIDLO": "42.97", "ASKHI": "43.76"}, {"data": "2012/08/08", "OPENPRC": "43.38", "PRC": "42.88", "BIDLO": "42.65", "ASKHI": "43.48"}, {"data": "2012/08/09", "OPENPRC": "42.95", "PRC": "42.81", "BIDLO": "42.45", "ASKHI": "42.95"}, {"data": "2012/08/10", "OPENPRC": "42.34", "PRC": "42.08", "BIDLO": "41.64", "ASKHI": "42.45"}, {"data": "2012/08/13", "OPENPRC": "41.94", "PRC": "42.2", "BIDLO": "41.57", "ASKHI": "42.22"}, {"data": "2012/08/14", "OPENPRC": "42.48", "PRC": "42.28", "BIDLO": "42.14", "ASKHI": "42.5499"}, {"data": "2012/08/15", "OPENPRC": "42.14", "PRC": "42.95", "BIDLO": "42.14", "ASKHI": "43.11"}, {"data": "2012/08/16", "OPENPRC": "42.95", "PRC": "43.37", "BIDLO": "42.44", "ASKHI": "43.55"}, {"data": "2012/08/17", "OPENPRC": "43.55", "PRC": "44.31", "BIDLO": "42.88", "ASKHI": "44.43"}, {"data": "2012/08/20", "OPENPRC": "44.38", "PRC": "43.67", "BIDLO": "43.52", "ASKHI": "44.39"}, {"data": "2012/08/21", "OPENPRC": "43.69", "PRC": "43.63", "BIDLO": "43.43", "ASKHI": "43.99"}, {"data": "2012/08/22", "OPENPRC": "43.63", "PRC": "43.73", "BIDLO": "43.52", "ASKHI": "44.11"}, {"data": "2012/08/23", "OPENPRC": "43.65", "PRC": "43.76", "BIDLO": "43.13", "ASKHI": "43.87"}, {"data": "2012/08/24", "OPENPRC": "43.66", "PRC": "44.71", "BIDLO": "43.49", "ASKHI": "45.05"}, {"data": "2012/08/27", "OPENPRC": "44.82", "PRC": "44.39", "BIDLO": "44.16", "ASKHI": "44.99"}, {"data": "2012/08/28", "OPENPRC": "44.32", "PRC": "44.18", "BIDLO": "43.9", "ASKHI": "44.77"}, {"data": "2012/08/29", "OPENPRC": "44.15", "PRC": "43.92", "BIDLO": "43.63", "ASKHI": "44.4"}, {"data": "2012/08/30", "OPENPRC": "43.55", "PRC": "43.07", "BIDLO": "42.96", "ASKHI": "43.58"}, {"data": "2012/08/31", "OPENPRC": "43.3", "PRC": "43.09", "BIDLO": "42.87", "ASKHI": "43.655"}, {"data": "2012/09/04", "OPENPRC": "42.86", "PRC": "43.37", "BIDLO": "42.78", "ASKHI": "43.82"}, {"data": "2012/09/05", "OPENPRC": "42.71", "PRC": "42.24", "BIDLO": "41.54", "ASKHI": "43.16"}, {"data": "2012/09/06", "OPENPRC": "42.32", "PRC": "42.18", "BIDLO": "41.75", "ASKHI": "42.585"}, {"data": "2012/09/07", "OPENPRC": "42.37", "PRC": "42.13", "BIDLO": "41.75", "ASKHI": "42.43"}, {"data": "2012/09/10", "OPENPRC": "42.13", "PRC": "42.25", "BIDLO": "41.84", "ASKHI": "42.82"}, {"data": "2012/09/11", "OPENPRC": "42.15", "PRC": "42.53", "BIDLO": "42.09", "ASKHI": "42.73"}, {"data": "2012/09/12", "OPENPRC": "42.54", "PRC": "42.68", "BIDLO": "42.52", "ASKHI": "43.06"}, {"data": "2012/09/13", "OPENPRC": "42.39", "PRC": "42.865", "BIDLO": "41.81", "ASKHI": "43.36"}, {"data": "2012/09/14", "OPENPRC": "42.8", "PRC": "44.26", "BIDLO": "42.67", "ASKHI": "44.29"}, {"data": "2012/09/17", "OPENPRC": "44.08", "PRC": "43.98", "BIDLO": "43.65", "ASKHI": "44.405"}, {"data": "2012/09/18", "OPENPRC": "43.89", "PRC": "43.32", "BIDLO": "43.21", "ASKHI": "44.04"}, {"data": "2012/09/19", "OPENPRC": "43.46", "PRC": "43.72", "BIDLO": "43.02", "ASKHI": "44.04"}, {"data": "2012/09/20", "OPENPRC": "43.64", "PRC": "43.91", "BIDLO": "43.19", "ASKHI": "44.11"}, {"data": "2012/09/21", "OPENPRC": "43.98", "PRC": "43.64", "BIDLO": "43.38", "ASKHI": "44.46"}, {"data": "2012/09/24", "OPENPRC": "43.52", "PRC": "43.53", "BIDLO": "43.15", "ASKHI": "43.79"}, {"data": "2012/09/25", "OPENPRC": "43.59", "PRC": "43.29", "BIDLO": "43.26", "ASKHI": "44.3"}, {"data": "2012/09/26", "OPENPRC": "43.35", "PRC": "42.58", "BIDLO": "42.48", "ASKHI": "43.71"}, {"data": "2012/09/27", "OPENPRC": "42.662", "PRC": "42.835", "BIDLO": "42.29", "ASKHI": "43.24"}, {"data": "2012/09/28", "OPENPRC": "42.69", "PRC": "42.99", "BIDLO": "42.28", "ASKHI": "43.09"}, {"data": "2012/10/01", "OPENPRC": "43.42", "PRC": "44.595", "BIDLO": "43.0", "ASKHI": "45.07"}, {"data": "2012/10/02", "OPENPRC": "44.85", "PRC": "44.3", "BIDLO": "44.0", "ASKHI": "45.22"}, {"data": "2012/10/03", "OPENPRC": "44.35", "PRC": "44.34", "BIDLO": "44.0101", "ASKHI": "44.63"}, {"data": "2012/10/04", "OPENPRC": "44.62", "PRC": "44.5", "BIDLO": "44.37", "ASKHI": "45.28"}, {"data": "2012/10/05", "OPENPRC": "44.73", "PRC": "44.18", "BIDLO": "44.04", "ASKHI": "44.94"}, {"data": "2012/10/08", "OPENPRC": "44.13", "PRC": "43.96", "BIDLO": "43.7", "ASKHI": "44.19"}, {"data": "2012/10/09", "OPENPRC": "43.8", "PRC": "42.78", "BIDLO": "42.67", "ASKHI": "43.93"}, {"data": "2012/10/10", "OPENPRC": "42.96", "PRC": "42.32", "BIDLO": "42.24", "ASKHI": "43.45"}, {"data": "2012/10/11", "OPENPRC": "44.69", "PRC": "45.89", "BIDLO": "44.0", "ASKHI": "47.17"}, {"data": "2012/10/12", "OPENPRC": "45.84", "PRC": "45.32", "BIDLO": "44.84", "ASKHI": "46.05"}, {"data": "2012/10/15", "OPENPRC": "45.58", "PRC": "45.55", "BIDLO": "45.03", "ASKHI": "45.86"}, {"data": "2012/10/16", "OPENPRC": "45.0", "PRC": "44.92", "BIDLO": "44.67", "ASKHI": "45.62"}, {"data": "2012/10/17", "OPENPRC": "44.94", "PRC": "45.4404", "BIDLO": "44.72", "ASKHI": "45.6"}, {"data": "2012/10/18", "OPENPRC": "45.32", "PRC": "44.74", "BIDLO": "44.74", "ASKHI": "45.375"}, {"data": "2012/10/19", "OPENPRC": "44.66", "PRC": "43.76", "BIDLO": "43.56", "ASKHI": "45.04"}, {"data": "2012/10/22", "OPENPRC": "43.78", "PRC": "44.4", "BIDLO": "43.62", "ASKHI": "44.825"}, {"data": "2012/10/23", "OPENPRC": "43.97", "PRC": "44.11", "BIDLO": "43.73", "ASKHI": "44.47"}, {"data": "2012/10/24", "OPENPRC": "44.25", "PRC": "43.72", "BIDLO": "43.68", "ASKHI": "44.63"}, {"data": "2012/10/25", "OPENPRC": "43.82", "PRC": "43.05", "BIDLO": "42.91", "ASKHI": "44.165"}, {"data": "2012/10/26", "OPENPRC": "43.05", "PRC": "43.24", "BIDLO": "42.84", "ASKHI": "43.435"}, {"data": "2012/10/31", "OPENPRC": "43.5", "PRC": "44.7", "BIDLO": "43.4", "ASKHI": "45.41"}, {"data": "2012/11/01", "OPENPRC": "44.94", "PRC": "45.06", "BIDLO": "44.71", "ASKHI": "45.13"}, {"data": "2012/11/02", "OPENPRC": "45.25", "PRC": "43.8", "BIDLO": "43.8", "ASKHI": "45.25"}, {"data": "2012/11/05", "OPENPRC": "42.74", "PRC": "43.19", "BIDLO": "42.28", "ASKHI": "43.34"}, {"data": "2012/11/06", "OPENPRC": "43.31", "PRC": "43.18", "BIDLO": "42.58", "ASKHI": "43.43"}, {"data": "2012/11/07", "OPENPRC": "42.88", "PRC": "42.63", "BIDLO": "42.1", "ASKHI": "43.14"}, {"data": "2012/11/08", "OPENPRC": "42.45", "PRC": "41.99", "BIDLO": "41.93", "ASKHI": "42.78"}, {"data": "2012/11/09", "OPENPRC": "42.86", "PRC": "42.31", "BIDLO": "42.221", "ASKHI": "43.04"}, {"data": "2012/11/12", "OPENPRC": "42.37", "PRC": "41.76", "BIDLO": "41.73", "ASKHI": "42.52"}, {"data": "2012/11/13", "OPENPRC": "41.54", "PRC": "41.39", "BIDLO": "41.29", "ASKHI": "41.99"}, {"data": "2012/11/14", "OPENPRC": "41.44", "PRC": "40.2", "BIDLO": "40.12", "ASKHI": "41.5"}, {"data": "2012/11/15", "OPENPRC": "40.02", "PRC": "40.95", "BIDLO": "40.0", "ASKHI": "41.0"}, {"data": "2012/11/16", "OPENPRC": "40.84", "PRC": "41.0", "BIDLO": "40.49", "ASKHI": "41.24"}, {"data": "2012/11/19", "OPENPRC": "41.0", "PRC": "41.47", "BIDLO": "40.98", "ASKHI": "41.56"}, {"data": "2012/11/20", "OPENPRC": "41.52", "PRC": "40.91", "BIDLO": "40.77", "ASKHI": "41.664"}, {"data": "2012/11/21", "OPENPRC": "41.08", "PRC": "40.77", "BIDLO": "40.67", "ASKHI": "41.42"}, {"data": "2012/11/23", "OPENPRC": "40.83", "PRC": "41.14", "BIDLO": "40.545", "ASKHI": "41.27"}, {"data": "2012/11/26", "OPENPRC": "41.07", "PRC": "41.19", "BIDLO": "40.37", "ASKHI": "41.39"}, {"data": "2012/11/27", "OPENPRC": "41.12", "PRC": "40.85", "BIDLO": "40.83", "ASKHI": "41.36"}, {"data": "2012/11/28", "OPENPRC": "40.63", "PRC": "41.02", "BIDLO": "40.275", "ASKHI": "41.09"}, {"data": "2012/11/29", "OPENPRC": "41.4", "PRC": "42.2", "BIDLO": "41.19", "ASKHI": "42.42"}, {"data": "2012/11/30", "OPENPRC": "42.3", "PRC": "41.81", "BIDLO": "41.76", "ASKHI": "42.57"}, {"data": "2012/12/03", "OPENPRC": "41.97", "PRC": "42.09", "BIDLO": "41.47", "ASKHI": "42.29"}, {"data": "2012/12/04", "OPENPRC": "42.15", "PRC": "42.205", "BIDLO": "41.73", "ASKHI": "42.5"}, {"data": "2012/12/05", "OPENPRC": "41.87", "PRC": "41.52", "BIDLO": "41.06", "ASKHI": "41.99"}, {"data": "2012/12/06", "OPENPRC": "42.11", "PRC": "41.76", "BIDLO": "41.35", "ASKHI": "42.14"}, {"data": "2012/12/07", "OPENPRC": "41.96", "PRC": "42.12", "BIDLO": "41.72", "ASKHI": "42.42"}, {"data": "2012/12/10", "OPENPRC": "42.05", "PRC": "42.05", "BIDLO": "41.88", "ASKHI": "42.415"}, {"data": "2012/12/11", "OPENPRC": "42.19", "PRC": "43.02", "BIDLO": "42.05", "ASKHI": "43.39"}, {"data": "2012/12/12", "OPENPRC": "43.12", "PRC": "43.01", "BIDLO": "42.91", "ASKHI": "43.27"}, {"data": "2012/12/13", "OPENPRC": "42.93", "PRC": "42.98", "BIDLO": "42.905", "ASKHI": "43.29"}, {"data": "2012/12/14", "OPENPRC": "42.75", "PRC": "43.12", "BIDLO": "42.74", "ASKHI": "43.2"}, {"data": "2012/12/17", "OPENPRC": "43.29", "PRC": "43.7", "BIDLO": "43.11", "ASKHI": "43.71"}, {"data": "2012/12/18", "OPENPRC": "43.8", "PRC": "44.63", "BIDLO": "43.38", "ASKHI": "44.65"}, {"data": "2012/12/19", "OPENPRC": "44.58", "PRC": "44.5005", "BIDLO": "44.23", "ASKHI": "44.98"}, {"data": "2012/12/20", "OPENPRC": "44.63", "PRC": "45.02", "BIDLO": "44.18", "ASKHI": "45.05"}, {"data": "2012/12/21", "OPENPRC": "44.46", "PRC": "46.08", "BIDLO": "43.42", "ASKHI": "46.195"}, {"data": "2012/12/24", "OPENPRC": "45.85", "PRC": "46.36", "BIDLO": "45.85", "ASKHI": "46.36"}, {"data": "2012/12/26", "OPENPRC": "46.32", "PRC": "45.98", "BIDLO": "45.8901", "ASKHI": "46.36"}, {"data": "2012/12/27", "OPENPRC": "45.87", "PRC": "46.32", "BIDLO": "45.86", "ASKHI": "46.475"}, {"data": "2012/12/28", "OPENPRC": "46.09", "PRC": "46.18", "BIDLO": "46.09", "ASKHI": "47.04"}, {"data": "2012/12/31", "OPENPRC": "46.03", "PRC": "46.65", "BIDLO": "45.77", "ASKHI": "46.73"}]