[{"data": "2012/01/03", "OPENPRC": "18.8", "PRC": "18.55", "BIDLO": "18.49", "ASKHI": "18.9"}, {"data": "2012/01/04", "OPENPRC": "18.48", "PRC": "18.88", "BIDLO": "18.48", "ASKHI": "19.035"}, {"data": "2012/01/05", "OPENPRC": "18.31", "PRC": "18.27", "BIDLO": "17.76", "ASKHI": "18.51"}, {"data": "2012/01/06", "OPENPRC": "18.19", "PRC": "18.0", "BIDLO": "17.97", "ASKHI": "18.36"}, {"data": "2012/01/09", "OPENPRC": "17.97", "PRC": "18.06", "BIDLO": "17.75", "ASKHI": "18.095"}, {"data": "2012/01/10", "OPENPRC": "18.24", "PRC": "18.14", "BIDLO": "17.93", "ASKHI": "18.24"}, {"data": "2012/01/11", "OPENPRC": "18.04", "PRC": "17.94", "BIDLO": "17.8", "ASKHI": "18.1"}, {"data": "2012/01/12", "OPENPRC": "18.0", "PRC": "18.14", "BIDLO": "17.81", "ASKHI": "18.19"}, {"data": "2012/01/13", "OPENPRC": "18.02", "PRC": "18.26", "BIDLO": "17.99", "ASKHI": "18.39"}, {"data": "2012/01/17", "OPENPRC": "18.63", "PRC": "18.26", "BIDLO": "18.24", "ASKHI": "18.71"}, {"data": "2012/01/18", "OPENPRC": "18.23", "PRC": "18.64", "BIDLO": "18.17", "ASKHI": "18.68"}, {"data": "2012/01/19", "OPENPRC": "18.67", "PRC": "19.37", "BIDLO": "18.6", "ASKHI": "19.67"}, {"data": "2012/01/20", "OPENPRC": "19.42", "PRC": "18.63", "BIDLO": "18.43", "ASKHI": "19.44"}, {"data": "2012/01/23", "OPENPRC": "18.62", "PRC": "18.68", "BIDLO": "18.46", "ASKHI": "18.81"}, {"data": "2012/01/24", "OPENPRC": "18.54", "PRC": "18.63", "BIDLO": "18.4", "ASKHI": "18.66"}, {"data": "2012/01/25", "OPENPRC": "18.62", "PRC": "19.0", "BIDLO": "18.56", "ASKHI": "19.05"}, {"data": "2012/01/26", "OPENPRC": "19.02", "PRC": "18.78", "BIDLO": "18.68", "ASKHI": "19.17"}, {"data": "2012/01/27", "OPENPRC": "18.74", "PRC": "18.93", "BIDLO": "18.68", "ASKHI": "19.0"}, {"data": "2012/01/30", "OPENPRC": "18.81", "PRC": "18.83", "BIDLO": "18.53", "ASKHI": "18.9"}, {"data": "2012/01/31", "OPENPRC": "18.9", "PRC": "18.98", "BIDLO": "18.765", "ASKHI": "19.19"}, {"data": "2012/02/01", "OPENPRC": "19.1", "PRC": "19.45", "BIDLO": "19.09", "ASKHI": "19.56"}, {"data": "2012/02/02", "OPENPRC": "21.06", "PRC": "21.52", "BIDLO": "20.42", "ASKHI": "21.65"}, {"data": "2012/02/03", "OPENPRC": "21.48", "PRC": "21.71", "BIDLO": "21.33", "ASKHI": "21.86"}, {"data": "2012/02/06", "OPENPRC": "21.45", "PRC": "21.67", "BIDLO": "21.36", "ASKHI": "21.685"}, {"data": "2012/02/07", "OPENPRC": "21.62", "PRC": "21.68", "BIDLO": "21.48", "ASKHI": "21.88"}, {"data": "2012/02/08", "OPENPRC": "21.65", "PRC": "21.28", "BIDLO": "21.23", "ASKHI": "21.66"}, {"data": "2012/02/09", "OPENPRC": "21.33", "PRC": "21.41", "BIDLO": "21.15", "ASKHI": "21.45"}, {"data": "2012/02/10", "OPENPRC": "21.35", "PRC": "21.59", "BIDLO": "21.23", "ASKHI": "21.59"}, {"data": "2012/02/13", "OPENPRC": "21.67", "PRC": "21.72", "BIDLO": "21.5", "ASKHI": "21.77"}, {"data": "2012/02/14", "OPENPRC": "22.03", "PRC": "22.34", "BIDLO": "22.0", "ASKHI": "22.53"}, {"data": "2012/02/15", "OPENPRC": "22.43", "PRC": "22.4", "BIDLO": "22.29", "ASKHI": "22.72"}, {"data": "2012/02/16", "OPENPRC": "22.4", "PRC": "22.45", "BIDLO": "22.29", "ASKHI": "22.69"}, {"data": "2012/02/17", "OPENPRC": "22.56", "PRC": "22.72", "BIDLO": "22.45", "ASKHI": "22.88"}, {"data": "2012/02/21", "OPENPRC": "22.87", "PRC": "22.83", "BIDLO": "22.68", "ASKHI": "22.96"}, {"data": "2012/02/22", "OPENPRC": "22.86", "PRC": "22.98", "BIDLO": "22.81", "ASKHI": "23.11"}, {"data": "2012/02/23", "OPENPRC": "22.87", "PRC": "23.52", "BIDLO": "22.76", "ASKHI": "23.57"}, {"data": "2012/02/24", "OPENPRC": "22.79", "PRC": "22.57", "BIDLO": "22.35", "ASKHI": "23.21"}, {"data": "2012/02/27", "OPENPRC": "22.58", "PRC": "23.07", "BIDLO": "22.53", "ASKHI": "23.17"}, {"data": "2012/02/28", "OPENPRC": "23.04", "PRC": "23.71", "BIDLO": "22.982", "ASKHI": "23.765"}, {"data": "2012/02/29", "OPENPRC": "23.52", "PRC": "23.36", "BIDLO": "23.345", "ASKHI": "23.71"}, {"data": "2012/03/01", "OPENPRC": "25.43", "PRC": "25.05", "BIDLO": "24.86", "ASKHI": "26.0"}, {"data": "2012/03/02", "OPENPRC": "24.65", "PRC": "24.41", "BIDLO": "24.39", "ASKHI": "24.97"}, {"data": "2012/03/05", "OPENPRC": "24.32", "PRC": "24.61", "BIDLO": "24.17", "ASKHI": "24.67"}, {"data": "2012/03/06", "OPENPRC": "24.32", "PRC": "24.27", "BIDLO": "24.18", "ASKHI": "24.49"}, {"data": "2012/03/07", "OPENPRC": "24.34", "PRC": "24.52", "BIDLO": "24.26", "ASKHI": "24.59"}, {"data": "2012/03/08", "OPENPRC": "24.64", "PRC": "24.89", "BIDLO": "24.54", "ASKHI": "25.19"}, {"data": "2012/03/09", "OPENPRC": "24.94", "PRC": "25.0", "BIDLO": "24.88", "ASKHI": "25.25"}, {"data": "2012/03/12", "OPENPRC": "24.89", "PRC": "25.09", "BIDLO": "24.82", "ASKHI": "25.15"}, {"data": "2012/03/13", "OPENPRC": "25.2", "PRC": "25.45", "BIDLO": "25.1", "ASKHI": "25.475"}, {"data": "2012/03/14", "OPENPRC": "25.48", "PRC": "25.44", "BIDLO": "25.15", "ASKHI": "25.57"}, {"data": "2012/03/15", "OPENPRC": "25.24", "PRC": "25.64", "BIDLO": "24.97", "ASKHI": "25.67"}, {"data": "2012/03/16", "OPENPRC": "25.44", "PRC": "25.39", "BIDLO": "25.04", "ASKHI": "25.5"}, {"data": "2012/03/19", "OPENPRC": "25.63", "PRC": "26.08", "BIDLO": "25.55", "ASKHI": "26.14"}, {"data": "2012/03/20", "OPENPRC": "25.65", "PRC": "26.13", "BIDLO": "25.49", "ASKHI": "26.3"}, {"data": "2012/03/21", "OPENPRC": "26.1", "PRC": "26.06", "BIDLO": "25.96", "ASKHI": "26.34"}, {"data": "2012/03/22", "OPENPRC": "25.91", "PRC": "26.24", "BIDLO": "25.75", "ASKHI": "26.28"}, {"data": "2012/03/23", "OPENPRC": "26.43", "PRC": "26.46", "BIDLO": "25.91", "ASKHI": "26.49"}, {"data": "2012/03/26", "OPENPRC": "26.54", "PRC": "26.87", "BIDLO": "26.52", "ASKHI": "26.89"}, {"data": "2012/03/27", "OPENPRC": "26.85", "PRC": "26.68", "BIDLO": "26.62", "ASKHI": "26.885"}, {"data": "2012/03/28", "OPENPRC": "26.68", "PRC": "26.26", "BIDLO": "25.92", "ASKHI": "26.69"}, {"data": "2012/03/29", "OPENPRC": "26.17", "PRC": "26.1", "BIDLO": "25.82", "ASKHI": "26.31"}, {"data": "2012/03/30", "OPENPRC": "26.9", "PRC": "26.14", "BIDLO": "26.14", "ASKHI": "27.0"}, {"data": "2012/04/02", "OPENPRC": "26.37", "PRC": "26.44", "BIDLO": "26.26", "ASKHI": "26.75"}, {"data": "2012/04/03", "OPENPRC": "25.88", "PRC": "26.05", "BIDLO": "25.73", "ASKHI": "26.45"}, {"data": "2012/04/04", "OPENPRC": "26.26", "PRC": "26.65", "BIDLO": "25.98", "ASKHI": "26.71"}, {"data": "2012/04/05", "OPENPRC": "26.52", "PRC": "26.45", "BIDLO": "26.22", "ASKHI": "26.85"}, {"data": "2012/04/09", "OPENPRC": "26.19", "PRC": "26.12", "BIDLO": "25.91", "ASKHI": "26.28"}, {"data": "2012/04/10", "OPENPRC": "26.03", "PRC": "25.23", "BIDLO": "25.19", "ASKHI": "26.03"}, {"data": "2012/04/11", "OPENPRC": "25.44", "PRC": "25.48", "BIDLO": "25.33", "ASKHI": "25.64"}, {"data": "2012/04/12", "OPENPRC": "25.62", "PRC": "25.96", "BIDLO": "25.54", "ASKHI": "26.03"}, {"data": "2012/04/13", "OPENPRC": "25.94", "PRC": "26.56", "BIDLO": "25.94", "ASKHI": "26.61"}, {"data": "2012/04/16", "OPENPRC": "26.71", "PRC": "26.43", "BIDLO": "26.23", "ASKHI": "26.96"}, {"data": "2012/04/17", "OPENPRC": "26.46", "PRC": "27.02", "BIDLO": "26.4", "ASKHI": "27.07"}, {"data": "2012/04/18", "OPENPRC": "26.94", "PRC": "27.62", "BIDLO": "26.83", "ASKHI": "27.66"}, {"data": "2012/04/19", "OPENPRC": "27.55", "PRC": "27.5", "BIDLO": "27.3", "ASKHI": "27.82"}, {"data": "2012/04/20", "OPENPRC": "27.73", "PRC": "27.85", "BIDLO": "27.69", "ASKHI": "27.95"}, {"data": "2012/04/23", "OPENPRC": "27.52", "PRC": "27.69", "BIDLO": "27.37", "ASKHI": "27.77"}, {"data": "2012/04/24", "OPENPRC": "27.7", "PRC": "27.19", "BIDLO": "27.06", "ASKHI": "27.75"}, {"data": "2012/04/25", "OPENPRC": "27.53", "PRC": "27.89", "BIDLO": "27.38", "ASKHI": "27.99"}, {"data": "2012/04/26", "OPENPRC": "27.82", "PRC": "28.4", "BIDLO": "27.685", "ASKHI": "28.425"}, {"data": "2012/04/27", "OPENPRC": "28.5", "PRC": "28.53", "BIDLO": "28.22", "ASKHI": "28.77"}, {"data": "2012/04/30", "OPENPRC": "28.65", "PRC": "28.5", "BIDLO": "28.3", "ASKHI": "29.01"}, {"data": "2012/05/01", "OPENPRC": "28.61", "PRC": "28.53", "BIDLO": "28.45", "ASKHI": "29.23"}, {"data": "2012/05/02", "OPENPRC": "28.32", "PRC": "29.14", "BIDLO": "27.81", "ASKHI": "29.19"}, {"data": "2012/05/03", "OPENPRC": "28.55", "PRC": "28.67", "BIDLO": "28.42", "ASKHI": "29.02"}, {"data": "2012/05/04", "OPENPRC": "28.49", "PRC": "28.2", "BIDLO": "28.14", "ASKHI": "28.92"}, {"data": "2012/05/07", "OPENPRC": "28.0", "PRC": "28.57", "BIDLO": "28.0", "ASKHI": "28.685"}, {"data": "2012/05/08", "OPENPRC": "28.36", "PRC": "28.05", "BIDLO": "27.44", "ASKHI": "28.4"}, {"data": "2012/05/09", "OPENPRC": "27.76", "PRC": "27.91", "BIDLO": "27.37", "ASKHI": "28.1"}, {"data": "2012/05/10", "OPENPRC": "28.17", "PRC": "28.12", "BIDLO": "27.82", "ASKHI": "28.4"}, {"data": "2012/05/11", "OPENPRC": "27.98", "PRC": "28.0", "BIDLO": "27.73", "ASKHI": "28.46"}, {"data": "2012/05/14", "OPENPRC": "27.72", "PRC": "27.37", "BIDLO": "27.34", "ASKHI": "27.75"}, {"data": "2012/05/15", "OPENPRC": "27.53", "PRC": "27.43", "BIDLO": "27.3425", "ASKHI": "27.88"}, {"data": "2012/05/16", "OPENPRC": "27.52", "PRC": "27.1", "BIDLO": "27.01", "ASKHI": "27.73"}, {"data": "2012/05/17", "OPENPRC": "27.17", "PRC": "26.31", "BIDLO": "26.19", "ASKHI": "27.24"}, {"data": "2012/05/18", "OPENPRC": "26.56", "PRC": "25.71", "BIDLO": "25.31", "ASKHI": "26.72"}, {"data": "2012/05/21", "OPENPRC": "25.83", "PRC": "26.51", "BIDLO": "25.63", "ASKHI": "26.68"}, {"data": "2012/05/22", "OPENPRC": "26.8", "PRC": "26.49", "BIDLO": "26.38", "ASKHI": "27.03"}, {"data": "2012/05/23", "OPENPRC": "26.33", "PRC": "26.76", "BIDLO": "26.19", "ASKHI": "26.86"}, {"data": "2012/05/24", "OPENPRC": "26.78", "PRC": "26.99", "BIDLO": "26.78", "ASKHI": "27.26"}, {"data": "2012/05/25", "OPENPRC": "27.0", "PRC": "27.16", "BIDLO": "26.99", "ASKHI": "27.38"}, {"data": "2012/05/29", "OPENPRC": "27.43", "PRC": "27.7", "BIDLO": "27.23", "ASKHI": "27.725"}, {"data": "2012/05/30", "OPENPRC": "27.63", "PRC": "26.67", "BIDLO": "26.64", "ASKHI": "27.66"}, {"data": "2012/05/31", "OPENPRC": "26.47", "PRC": "26.5", "BIDLO": "26.12", "ASKHI": "26.73"}, {"data": "2012/06/01", "OPENPRC": "26.06", "PRC": "25.26", "BIDLO": "25.07", "ASKHI": "26.19"}, {"data": "2012/06/04", "OPENPRC": "25.35", "PRC": "25.48", "BIDLO": "25.02", "ASKHI": "25.55"}, {"data": "2012/06/05", "OPENPRC": "25.26", "PRC": "25.53", "BIDLO": "25.18", "ASKHI": "25.61"}, {"data": "2012/06/06", "OPENPRC": "25.71", "PRC": "25.69", "BIDLO": "25.54", "ASKHI": "25.85"}, {"data": "2012/06/07", "OPENPRC": "25.81", "PRC": "25.7", "BIDLO": "25.55", "ASKHI": "26.06"}, {"data": "2012/06/08", "OPENPRC": "25.52", "PRC": "26.24", "BIDLO": "25.45", "ASKHI": "26.24"}, {"data": "2012/06/11", "OPENPRC": "26.45", "PRC": "25.56", "BIDLO": "25.51", "ASKHI": "26.47"}, {"data": "2012/06/12", "OPENPRC": "25.61", "PRC": "26.05", "BIDLO": "25.61", "ASKHI": "26.12"}, {"data": "2012/06/13", "OPENPRC": "25.89", "PRC": "25.62", "BIDLO": "25.545", "ASKHI": "26.03"}, {"data": "2012/06/14", "OPENPRC": "25.65", "PRC": "26.42", "BIDLO": "25.59", "ASKHI": "26.5"}, {"data": "2012/06/15", "OPENPRC": "26.51", "PRC": "26.73", "BIDLO": "26.42", "ASKHI": "26.84"}, {"data": "2012/06/18", "OPENPRC": "26.67", "PRC": "27.01", "BIDLO": "26.5", "ASKHI": "27.17"}, {"data": "2012/06/19", "OPENPRC": "27.13", "PRC": "27.33", "BIDLO": "27.09", "ASKHI": "27.45"}, {"data": "2012/06/20", "OPENPRC": "27.45", "PRC": "27.6", "BIDLO": "27.26", "ASKHI": "27.74"}, {"data": "2012/06/21", "OPENPRC": "27.64", "PRC": "27.3", "BIDLO": "27.21", "ASKHI": "27.8"}, {"data": "2012/06/22", "OPENPRC": "27.54", "PRC": "27.36", "BIDLO": "27.13", "ASKHI": "27.57"}, {"data": "2012/06/25", "OPENPRC": "27.04", "PRC": "26.48", "BIDLO": "26.435", "ASKHI": "27.15"}, {"data": "2012/06/26", "OPENPRC": "26.5", "PRC": "26.56", "BIDLO": "26.25", "ASKHI": "26.72"}, {"data": "2012/06/27", "OPENPRC": "26.63", "PRC": "26.42", "BIDLO": "26.27", "ASKHI": "26.85"}, {"data": "2012/06/28", "OPENPRC": "26.26", "PRC": "26.36", "BIDLO": "25.97", "ASKHI": "26.77"}, {"data": "2012/06/29", "OPENPRC": "26.67", "PRC": "27.36", "BIDLO": "26.67", "ASKHI": "27.44"}, {"data": "2012/07/02", "OPENPRC": "27.53", "PRC": "27.52", "BIDLO": "26.96", "ASKHI": "27.68"}, {"data": "2012/07/03", "OPENPRC": "27.44", "PRC": "27.69", "BIDLO": "27.38", "ASKHI": "27.9"}, {"data": "2012/07/05", "OPENPRC": "27.61", "PRC": "27.97", "BIDLO": "27.61", "ASKHI": "28.12"}, {"data": "2012/07/06", "OPENPRC": "27.78", "PRC": "27.88", "BIDLO": "27.64", "ASKHI": "28.03"}, {"data": "2012/07/09", "OPENPRC": "27.76", "PRC": "28.19", "BIDLO": "27.73", "ASKHI": "28.33"}, {"data": "2012/07/10", "OPENPRC": "28.36", "PRC": "27.7", "BIDLO": "27.55", "ASKHI": "28.53"}, {"data": "2012/07/11", "OPENPRC": "27.39", "PRC": "27.16", "BIDLO": "27.0", "ASKHI": "27.64"}, {"data": "2012/07/12", "OPENPRC": "26.96", "PRC": "27.18", "BIDLO": "26.57", "ASKHI": "27.29"}, {"data": "2012/07/13", "OPENPRC": "27.2", "PRC": "27.9", "BIDLO": "27.18", "ASKHI": "27.96"}, {"data": "2012/07/16", "OPENPRC": "27.82", "PRC": "27.97", "BIDLO": "27.66", "ASKHI": "28.22"}, {"data": "2012/07/17", "OPENPRC": "28.14", "PRC": "28.47", "BIDLO": "28.05", "ASKHI": "28.6"}, {"data": "2012/07/18", "OPENPRC": "28.38", "PRC": "29.12", "BIDLO": "28.33", "ASKHI": "29.28"}, {"data": "2012/07/19", "OPENPRC": "29.25", "PRC": "29.48", "BIDLO": "29.11", "ASKHI": "29.54"}, {"data": "2012/07/20", "OPENPRC": "29.13", "PRC": "29.2", "BIDLO": "28.92", "ASKHI": "29.325"}, {"data": "2012/07/23", "OPENPRC": "28.65", "PRC": "29.17", "BIDLO": "28.45", "ASKHI": "29.29"}, {"data": "2012/07/24", "OPENPRC": "29.23", "PRC": "28.92", "BIDLO": "28.635", "ASKHI": "29.32"}, {"data": "2012/07/25", "OPENPRC": "29.12", "PRC": "29.29", "BIDLO": "29.06", "ASKHI": "29.59"}, {"data": "2012/07/26", "OPENPRC": "29.75", "PRC": "29.65", "BIDLO": "29.24", "ASKHI": "29.94"}, {"data": "2012/07/27", "OPENPRC": "29.91", "PRC": "29.91", "BIDLO": "29.74", "ASKHI": "30.17"}, {"data": "2012/07/30", "OPENPRC": "29.93", "PRC": "29.82", "BIDLO": "29.76", "ASKHI": "30.2"}, {"data": "2012/07/31", "OPENPRC": "29.69", "PRC": "29.49", "BIDLO": "29.39", "ASKHI": "29.74"}, {"data": "2012/08/01", "OPENPRC": "29.63", "PRC": "29.42", "BIDLO": "29.4", "ASKHI": "29.92"}, {"data": "2012/08/02", "OPENPRC": "31.955", "PRC": "33.17", "BIDLO": "31.51", "ASKHI": "33.69"}, {"data": "2012/08/03", "OPENPRC": "32.98", "PRC": "33.46", "BIDLO": "32.85", "ASKHI": "33.99"}, {"data": "2012/08/06", "OPENPRC": "33.43", "PRC": "33.75", "BIDLO": "33.37", "ASKHI": "33.88"}, {"data": "2012/08/07", "OPENPRC": "33.84", "PRC": "33.94", "BIDLO": "33.82", "ASKHI": "34.12"}, {"data": "2012/08/08", "OPENPRC": "33.78", "PRC": "34.64", "BIDLO": "33.75", "ASKHI": "34.92"}, {"data": "2012/08/09", "OPENPRC": "34.57", "PRC": "34.42", "BIDLO": "34.17", "ASKHI": "34.66"}, {"data": "2012/08/10", "OPENPRC": "34.55", "PRC": "34.21", "BIDLO": "33.89", "ASKHI": "34.55"}, {"data": "2012/08/13", "OPENPRC": "34.2", "PRC": "34.63", "BIDLO": "34.16", "ASKHI": "34.63"}, {"data": "2012/08/14", "OPENPRC": "34.76", "PRC": "34.61", "BIDLO": "34.51", "ASKHI": "34.89"}, {"data": "2012/08/15", "OPENPRC": "34.74", "PRC": "34.61", "BIDLO": "34.55", "ASKHI": "34.89"}, {"data": "2012/08/16", "OPENPRC": "34.69", "PRC": "34.34", "BIDLO": "33.35", "ASKHI": "34.83"}, {"data": "2012/08/17", "OPENPRC": "35.11", "PRC": "35.99", "BIDLO": "35.01", "ASKHI": "36.23"}, {"data": "2012/08/20", "OPENPRC": "35.94", "PRC": "35.34", "BIDLO": "35.14", "ASKHI": "36.03"}, {"data": "2012/08/21", "OPENPRC": "35.63", "PRC": "35.32", "BIDLO": "35.13", "ASKHI": "35.78"}, {"data": "2012/08/22", "OPENPRC": "35.17", "PRC": "35.3", "BIDLO": "35.125", "ASKHI": "35.48"}, {"data": "2012/08/23", "OPENPRC": "35.07", "PRC": "34.97", "BIDLO": "34.845", "ASKHI": "35.2"}, {"data": "2012/08/24", "OPENPRC": "34.67", "PRC": "35.12", "BIDLO": "34.67", "ASKHI": "35.17"}, {"data": "2012/08/27", "OPENPRC": "35.1", "PRC": "35.09", "BIDLO": "35.04", "ASKHI": "35.24"}, {"data": "2012/08/28", "OPENPRC": "35.12", "PRC": "35.11", "BIDLO": "34.9", "ASKHI": "35.29"}, {"data": "2012/08/29", "OPENPRC": "35.09", "PRC": "35.17", "BIDLO": "35.03", "ASKHI": "35.26"}, {"data": "2012/08/30", "OPENPRC": "35.7", "PRC": "36.11", "BIDLO": "35.38", "ASKHI": "36.6"}, {"data": "2012/08/31", "OPENPRC": "36.11", "PRC": "35.82", "BIDLO": "35.68", "ASKHI": "36.24"}, {"data": "2012/09/04", "OPENPRC": "35.71", "PRC": "35.81", "BIDLO": "35.53", "ASKHI": "35.9"}, {"data": "2012/09/05", "OPENPRC": "35.57", "PRC": "35.45", "BIDLO": "35.23", "ASKHI": "35.69"}, {"data": "2012/09/06", "OPENPRC": "35.57", "PRC": "36.09", "BIDLO": "35.57", "ASKHI": "36.135"}, {"data": "2012/09/07", "OPENPRC": "36.19", "PRC": "35.93", "BIDLO": "35.92", "ASKHI": "36.315"}, {"data": "2012/09/10", "OPENPRC": "35.84", "PRC": "35.48", "BIDLO": "35.46", "ASKHI": "35.91"}, {"data": "2012/09/11", "OPENPRC": "35.39", "PRC": "35.13", "BIDLO": "35.11", "ASKHI": "35.63"}, {"data": "2012/09/12", "OPENPRC": "35.3", "PRC": "35.54", "BIDLO": "35.3", "ASKHI": "35.68"}, {"data": "2012/09/13", "OPENPRC": "35.44", "PRC": "35.65", "BIDLO": "35.26", "ASKHI": "35.9"}, {"data": "2012/09/14", "OPENPRC": "35.63", "PRC": "35.2", "BIDLO": "35.08", "ASKHI": "35.77"}, {"data": "2012/09/17", "OPENPRC": "35.01", "PRC": "36.05", "BIDLO": "34.79", "ASKHI": "36.14"}, {"data": "2012/09/18", "OPENPRC": "35.86", "PRC": "36.01", "BIDLO": "35.64", "ASKHI": "36.19"}, {"data": "2012/09/19", "OPENPRC": "35.99", "PRC": "35.93", "BIDLO": "35.8", "ASKHI": "36.23"}, {"data": "2012/09/20", "OPENPRC": "35.82", "PRC": "36.14", "BIDLO": "35.5175", "ASKHI": "36.18"}, {"data": "2012/09/21", "OPENPRC": "36.47", "PRC": "36.19", "BIDLO": "36.06", "ASKHI": "36.73"}, {"data": "2012/09/24", "OPENPRC": "36.0", "PRC": "35.89", "BIDLO": "35.64", "ASKHI": "36.15"}, {"data": "2012/09/25", "OPENPRC": "35.96", "PRC": "35.46", "BIDLO": "35.46", "ASKHI": "36.21"}, {"data": "2012/09/26", "OPENPRC": "35.42", "PRC": "35.27", "BIDLO": "34.95", "ASKHI": "35.78"}, {"data": "2012/09/27", "OPENPRC": "35.38", "PRC": "35.38", "BIDLO": "35.0", "ASKHI": "35.61"}, {"data": "2012/09/28", "OPENPRC": "35.33", "PRC": "35.78", "BIDLO": "35.24", "ASKHI": "35.92"}, {"data": "2012/10/01", "OPENPRC": "35.98", "PRC": "36.1", "BIDLO": "35.89", "ASKHI": "36.34"}, {"data": "2012/10/02", "OPENPRC": "36.49", "PRC": "36.14", "BIDLO": "35.95", "ASKHI": "36.49"}, {"data": "2012/10/03", "OPENPRC": "36.24", "PRC": "36.75", "BIDLO": "36.18", "ASKHI": "36.76"}, {"data": "2012/10/04", "OPENPRC": "37.11", "PRC": "37.1", "BIDLO": "36.62", "ASKHI": "37.43"}, {"data": "2012/10/05", "OPENPRC": "37.71", "PRC": "37.1", "BIDLO": "36.94", "ASKHI": "37.85"}, {"data": "2012/10/08", "OPENPRC": "36.94", "PRC": "37.27", "BIDLO": "36.94", "ASKHI": "37.44"}, {"data": "2012/10/09", "OPENPRC": "37.3", "PRC": "36.7", "BIDLO": "36.67", "ASKHI": "37.39"}, {"data": "2012/10/10", "OPENPRC": "36.77", "PRC": "36.62", "BIDLO": "36.5", "ASKHI": "36.9772"}, {"data": "2012/10/11", "OPENPRC": "36.88", "PRC": "36.34", "BIDLO": "36.34", "ASKHI": "37.05"}, {"data": "2012/10/12", "OPENPRC": "36.3", "PRC": "36.1", "BIDLO": "35.88", "ASKHI": "36.45"}, {"data": "2012/10/15", "OPENPRC": "36.32", "PRC": "36.28", "BIDLO": "36.06", "ASKHI": "36.44"}, {"data": "2012/10/16", "OPENPRC": "36.59", "PRC": "36.96", "BIDLO": "36.49", "ASKHI": "37.0"}, {"data": "2012/10/17", "OPENPRC": "37.0", "PRC": "36.79", "BIDLO": "36.54", "ASKHI": "37.115"}, {"data": "2012/10/18", "OPENPRC": "36.79", "PRC": "37.18", "BIDLO": "36.78", "ASKHI": "37.24"}, {"data": "2012/10/19", "OPENPRC": "37.24", "PRC": "36.37", "BIDLO": "36.165", "ASKHI": "37.25"}, {"data": "2012/10/22", "OPENPRC": "36.51", "PRC": "36.16", "BIDLO": "35.76", "ASKHI": "36.51"}, {"data": "2012/10/23", "OPENPRC": "35.78", "PRC": "35.47", "BIDLO": "35.1", "ASKHI": "35.78"}, {"data": "2012/10/24", "OPENPRC": "35.62", "PRC": "35.51", "BIDLO": "35.25", "ASKHI": "35.85"}, {"data": "2012/10/25", "OPENPRC": "35.71", "PRC": "35.17", "BIDLO": "34.8", "ASKHI": "35.85"}, {"data": "2012/10/26", "OPENPRC": "35.28", "PRC": "35.41", "BIDLO": "34.88", "ASKHI": "35.45"}, {"data": "2012/10/31", "OPENPRC": "34.9", "PRC": "35.72", "BIDLO": "34.57", "ASKHI": "35.86"}, {"data": "2012/11/01", "OPENPRC": "35.73", "PRC": "35.65", "BIDLO": "35.05", "ASKHI": "35.82"}, {"data": "2012/11/02", "OPENPRC": "35.78", "PRC": "35.11", "BIDLO": "35.09", "ASKHI": "35.81"}, {"data": "2012/11/05", "OPENPRC": "34.79", "PRC": "35.37", "BIDLO": "34.57", "ASKHI": "35.39"}, {"data": "2012/11/06", "OPENPRC": "35.41", "PRC": "35.94", "BIDLO": "35.32", "ASKHI": "36.15"}, {"data": "2012/11/07", "OPENPRC": "35.64", "PRC": "35.26", "BIDLO": "34.875", "ASKHI": "35.87"}, {"data": "2012/11/08", "OPENPRC": "35.2", "PRC": "34.07", "BIDLO": "34.06", "ASKHI": "35.32"}, {"data": "2012/11/09", "OPENPRC": "34.05", "PRC": "33.62", "BIDLO": "33.47", "ASKHI": "34.135"}, {"data": "2012/11/12", "OPENPRC": "33.79", "PRC": "33.5", "BIDLO": "33.18", "ASKHI": "33.82"}, {"data": "2012/11/13", "OPENPRC": "33.4", "PRC": "33.69", "BIDLO": "33.22", "ASKHI": "34.15"}, {"data": "2012/11/14", "OPENPRC": "34.3", "PRC": "33.63", "BIDLO": "33.5", "ASKHI": "34.87"}, {"data": "2012/11/15", "OPENPRC": "33.27", "PRC": "33.26", "BIDLO": "32.54", "ASKHI": "33.48"}, {"data": "2012/11/16", "OPENPRC": "34.46", "PRC": "33.59", "BIDLO": "33.18", "ASKHI": "34.73"}, {"data": "2012/11/19", "OPENPRC": "33.83", "PRC": "34.43", "BIDLO": "33.78", "ASKHI": "34.43"}, {"data": "2012/11/20", "OPENPRC": "34.4", "PRC": "34.9", "BIDLO": "34.37", "ASKHI": "35.09"}, {"data": "2012/11/21", "OPENPRC": "34.9", "PRC": "35.15", "BIDLO": "34.9", "ASKHI": "35.44"}, {"data": "2012/11/23", "OPENPRC": "35.32", "PRC": "35.5", "BIDLO": "35.26", "ASKHI": "35.61"}, {"data": "2012/11/26", "OPENPRC": "35.31", "PRC": "35.62", "BIDLO": "35.08", "ASKHI": "35.7"}, {"data": "2012/11/27", "OPENPRC": "35.68", "PRC": "35.15", "BIDLO": "35.13", "ASKHI": "35.84"}, {"data": "2012/11/28", "OPENPRC": "35.12", "PRC": "35.82", "BIDLO": "34.98", "ASKHI": "35.83"}, {"data": "2012/11/29", "OPENPRC": "34.84", "PRC": "34.36", "BIDLO": "34.31", "ASKHI": "35.53"}, {"data": "2012/11/30", "OPENPRC": "34.28", "PRC": "34.46", "BIDLO": "34.12", "ASKHI": "34.64"}, {"data": "2012/12/03", "OPENPRC": "34.52", "PRC": "34.51", "BIDLO": "34.14", "ASKHI": "34.69"}, {"data": "2012/12/04", "OPENPRC": "34.56", "PRC": "30.94", "BIDLO": "30.53", "ASKHI": "34.57"}, {"data": "2012/12/05", "OPENPRC": "31.13", "PRC": "31.81", "BIDLO": "31.121", "ASKHI": "31.95"}, {"data": "2012/12/06", "OPENPRC": "31.47", "PRC": "31.96", "BIDLO": "31.09", "ASKHI": "32.04"}, {"data": "2012/12/07", "OPENPRC": "32.1", "PRC": "31.81", "BIDLO": "31.5801", "ASKHI": "32.15"}, {"data": "2012/12/10", "OPENPRC": "31.52", "PRC": "30.89", "BIDLO": "30.22", "ASKHI": "31.6"}, {"data": "2012/12/11", "OPENPRC": "31.57", "PRC": "31.82", "BIDLO": "31.28", "ASKHI": "32.145"}, {"data": "2012/12/12", "OPENPRC": "31.74", "PRC": "31.43", "BIDLO": "31.391", "ASKHI": "31.8"}, {"data": "2012/12/13", "OPENPRC": "31.42", "PRC": "31.47", "BIDLO": "31.34", "ASKHI": "31.66"}, {"data": "2012/12/14", "OPENPRC": "31.35", "PRC": "31.45", "BIDLO": "31.34", "ASKHI": "31.59"}, {"data": "2012/12/17", "OPENPRC": "31.55", "PRC": "31.91", "BIDLO": "31.29", "ASKHI": "31.91"}, {"data": "2012/12/18", "OPENPRC": "31.68", "PRC": "32.02", "BIDLO": "31.45", "ASKHI": "32.27"}, {"data": "2012/12/19", "OPENPRC": "32.11", "PRC": "32.16", "BIDLO": "32.0", "ASKHI": "32.62"}, {"data": "2012/12/20", "OPENPRC": "32.19", "PRC": "31.75", "BIDLO": "31.25", "ASKHI": "32.19"}, {"data": "2012/12/21", "OPENPRC": "31.37", "PRC": "31.37", "BIDLO": "31.09", "ASKHI": "31.53"}, {"data": "2012/12/24", "OPENPRC": "31.41", "PRC": "31.37", "BIDLO": "31.3", "ASKHI": "31.65"}, {"data": "2012/12/26", "OPENPRC": "31.37", "PRC": "30.4", "BIDLO": "30.27", "ASKHI": "31.49"}, {"data": "2012/12/27", "OPENPRC": "30.46", "PRC": "30.69", "BIDLO": "30.145", "ASKHI": "30.75"}, {"data": "2012/12/28", "OPENPRC": "30.28", "PRC": "30.43", "BIDLO": "29.84", "ASKHI": "31.13"}, {"data": "2012/12/31", "OPENPRC": "30.44", "PRC": "31.04", "BIDLO": "30.23", "ASKHI": "31.06"}]