[{"data": "2012/01/03", "OPENPRC": "53.23", "PRC": "52.46", "BIDLO": "52.41", "ASKHI": "53.88"}, {"data": "2012/01/04", "OPENPRC": "52.36", "PRC": "52.3", "BIDLO": "51.88", "ASKHI": "52.53"}, {"data": "2012/01/05", "OPENPRC": "52.08", "PRC": "52.54", "BIDLO": "51.92", "ASKHI": "52.72"}, {"data": "2012/01/06", "OPENPRC": "52.39", "PRC": "53.12", "BIDLO": "52.09", "ASKHI": "53.31"}, {"data": "2012/01/09", "OPENPRC": "53.2", "PRC": "53.18", "BIDLO": "52.89", "ASKHI": "53.44"}, {"data": "2012/01/10", "OPENPRC": "53.46", "PRC": "54.75", "BIDLO": "53.36", "ASKHI": "54.92"}, {"data": "2012/01/11", "OPENPRC": "54.78", "PRC": "55.18", "BIDLO": "54.69", "ASKHI": "55.52"}, {"data": "2012/01/12", "OPENPRC": "55.36", "PRC": "55.285", "BIDLO": "54.81", "ASKHI": "55.6"}, {"data": "2012/01/13", "OPENPRC": "55.09", "PRC": "54.83", "BIDLO": "54.14", "ASKHI": "55.22"}, {"data": "2012/01/17", "OPENPRC": "55.5", "PRC": "55.25", "BIDLO": "55.03", "ASKHI": "55.85"}, {"data": "2012/01/18", "OPENPRC": "55.49", "PRC": "56.45", "BIDLO": "55.27", "ASKHI": "56.46"}, {"data": "2012/01/19", "OPENPRC": "56.53", "PRC": "57.1", "BIDLO": "56.36", "ASKHI": "57.14"}, {"data": "2012/01/20", "OPENPRC": "57.16", "PRC": "57.09", "BIDLO": "56.87", "ASKHI": "57.45"}, {"data": "2012/01/23", "OPENPRC": "56.91", "PRC": "57.41", "BIDLO": "56.57", "ASKHI": "57.595"}, {"data": "2012/01/24", "OPENPRC": "57.21", "PRC": "57.33", "BIDLO": "57.09", "ASKHI": "57.6"}, {"data": "2012/01/25", "OPENPRC": "57.52", "PRC": "57.52", "BIDLO": "56.63", "ASKHI": "57.67"}, {"data": "2012/01/26", "OPENPRC": "57.76", "PRC": "57.49", "BIDLO": "57.3", "ASKHI": "58.06"}, {"data": "2012/01/27", "OPENPRC": "57.36", "PRC": "57.35", "BIDLO": "57.06", "ASKHI": "57.87"}, {"data": "2012/01/30", "OPENPRC": "56.77", "PRC": "56.56", "BIDLO": "56.37", "ASKHI": "56.865"}, {"data": "2012/01/31", "OPENPRC": "56.79", "PRC": "56.44", "BIDLO": "55.52", "ASKHI": "56.867"}, {"data": "2012/02/01", "OPENPRC": "56.99", "PRC": "57.88", "BIDLO": "56.64", "ASKHI": "58.44"}, {"data": "2012/02/02", "OPENPRC": "57.88", "PRC": "57.86", "BIDLO": "57.69", "ASKHI": "58.45"}, {"data": "2012/02/03", "OPENPRC": "58.25", "PRC": "58.47", "BIDLO": "58.17", "ASKHI": "58.9"}, {"data": "2012/02/06", "OPENPRC": "57.88", "PRC": "57.9", "BIDLO": "57.82", "ASKHI": "58.45"}, {"data": "2012/02/07", "OPENPRC": "57.71", "PRC": "57.62", "BIDLO": "57.28", "ASKHI": "57.84"}, {"data": "2012/02/08", "OPENPRC": "57.56", "PRC": "57.56", "BIDLO": "56.44", "ASKHI": "57.68"}, {"data": "2012/02/09", "OPENPRC": "57.55", "PRC": "57.6", "BIDLO": "57.22", "ASKHI": "57.93"}, {"data": "2012/02/10", "OPENPRC": "56.98", "PRC": "56.68", "BIDLO": "56.33", "ASKHI": "57.1"}, {"data": "2012/02/13", "OPENPRC": "57.05", "PRC": "56.59", "BIDLO": "56.58", "ASKHI": "57.17"}, {"data": "2012/02/14", "OPENPRC": "56.42", "PRC": "56.77", "BIDLO": "56.4", "ASKHI": "56.78"}, {"data": "2012/02/15", "OPENPRC": "57.05", "PRC": "56.65", "BIDLO": "56.43", "ASKHI": "57.23"}, {"data": "2012/02/16", "OPENPRC": "56.83", "PRC": "58.01", "BIDLO": "56.7", "ASKHI": "58.09"}, {"data": "2012/02/17", "OPENPRC": "57.89", "PRC": "57.38", "BIDLO": "57.31", "ASKHI": "58.01"}, {"data": "2012/02/21", "OPENPRC": "57.79", "PRC": "57.52", "BIDLO": "57.21", "ASKHI": "57.94"}, {"data": "2012/02/22", "OPENPRC": "59.08", "PRC": "60.92", "BIDLO": "58.38", "ASKHI": "62.33"}, {"data": "2012/02/23", "OPENPRC": "59.08", "PRC": "58.68", "BIDLO": "58.53", "ASKHI": "60.0"}, {"data": "2012/02/24", "OPENPRC": "58.73", "PRC": "58.06", "BIDLO": "58.03", "ASKHI": "59.17"}, {"data": "2012/02/27", "OPENPRC": "57.71", "PRC": "57.89", "BIDLO": "57.55", "ASKHI": "58.275"}, {"data": "2012/02/28", "OPENPRC": "57.99", "PRC": "57.78", "BIDLO": "57.458", "ASKHI": "58.22"}, {"data": "2012/02/29", "OPENPRC": "57.79", "PRC": "57.84", "BIDLO": "57.46", "ASKHI": "58.01"}, {"data": "2012/03/01", "OPENPRC": "58.23", "PRC": "57.94", "BIDLO": "57.72", "ASKHI": "58.35"}, {"data": "2012/03/02", "OPENPRC": "57.89", "PRC": "57.27", "BIDLO": "57.18", "ASKHI": "57.9333"}, {"data": "2012/03/05", "OPENPRC": "57.13", "PRC": "56.87", "BIDLO": "56.44", "ASKHI": "57.41"}, {"data": "2012/03/06", "OPENPRC": "56.51", "PRC": "56.08", "BIDLO": "55.94", "ASKHI": "57.07"}, {"data": "2012/03/07", "OPENPRC": "56.44", "PRC": "57.13", "BIDLO": "56.2601", "ASKHI": "57.5"}, {"data": "2012/03/08", "OPENPRC": "57.37", "PRC": "57.22", "BIDLO": "57.07", "ASKHI": "57.525"}, {"data": "2012/03/09", "OPENPRC": "57.62", "PRC": "58.17", "BIDLO": "57.15", "ASKHI": "58.17"}, {"data": "2012/03/12", "OPENPRC": "58.3", "PRC": "58.62", "BIDLO": "58.16", "ASKHI": "58.75"}, {"data": "2012/03/13", "OPENPRC": "58.78", "PRC": "59.81", "BIDLO": "58.49", "ASKHI": "59.82"}, {"data": "2012/03/14", "OPENPRC": "59.63", "PRC": "59.69", "BIDLO": "59.44", "ASKHI": "59.87"}, {"data": "2012/03/15", "OPENPRC": "59.67", "PRC": "60.18", "BIDLO": "59.17", "ASKHI": "60.21"}, {"data": "2012/03/16", "OPENPRC": "60.05", "PRC": "60.14", "BIDLO": "59.9", "ASKHI": "60.56"}, {"data": "2012/03/19", "OPENPRC": "59.82", "PRC": "60.33", "BIDLO": "59.82", "ASKHI": "60.76"}, {"data": "2012/03/20", "OPENPRC": "59.88", "PRC": "60.04", "BIDLO": "59.65", "ASKHI": "60.1185"}, {"data": "2012/03/21", "OPENPRC": "60.04", "PRC": "60.12", "BIDLO": "59.77", "ASKHI": "60.28"}, {"data": "2012/03/22", "OPENPRC": "58.57", "PRC": "57.73", "BIDLO": "57.66", "ASKHI": "59.07"}, {"data": "2012/03/23", "OPENPRC": "57.86", "PRC": "57.71", "BIDLO": "56.97", "ASKHI": "58.03"}, {"data": "2012/03/26", "OPENPRC": "58.26", "PRC": "58.73", "BIDLO": "57.99", "ASKHI": "58.87"}, {"data": "2012/03/27", "OPENPRC": "58.95", "PRC": "59.48", "BIDLO": "58.5", "ASKHI": "59.65"}, {"data": "2012/03/28", "OPENPRC": "59.21", "PRC": "59.51", "BIDLO": "58.91", "ASKHI": "59.54"}, {"data": "2012/03/29", "OPENPRC": "59.3", "PRC": "59.83", "BIDLO": "58.91", "ASKHI": "59.94"}, {"data": "2012/03/30", "OPENPRC": "60.15", "PRC": "60.16", "BIDLO": "59.71", "ASKHI": "60.41"}, {"data": "2012/04/02", "OPENPRC": "60.07", "PRC": "60.62", "BIDLO": "59.73", "ASKHI": "60.92"}, {"data": "2012/04/03", "OPENPRC": "60.39", "PRC": "60.33", "BIDLO": "59.8", "ASKHI": "60.41"}, {"data": "2012/04/04", "OPENPRC": "59.81", "PRC": "59.38", "BIDLO": "59.06", "ASKHI": "59.98"}, {"data": "2012/04/05", "OPENPRC": "58.99", "PRC": "59.77", "BIDLO": "58.885", "ASKHI": "59.86"}, {"data": "2012/04/09", "OPENPRC": "58.9", "PRC": "59.105", "BIDLO": "58.6", "ASKHI": "59.31"}, {"data": "2012/04/10", "OPENPRC": "58.84", "PRC": "58.59", "BIDLO": "58.37", "ASKHI": "59.22"}, {"data": "2012/04/11", "OPENPRC": "58.94", "PRC": "60.03", "BIDLO": "58.65", "ASKHI": "60.06"}, {"data": "2012/04/12", "OPENPRC": "60.12", "PRC": "60.6", "BIDLO": "59.97", "ASKHI": "60.66"}, {"data": "2012/04/13", "OPENPRC": "60.16", "PRC": "60.34", "BIDLO": "59.77", "ASKHI": "60.85"}, {"data": "2012/04/16", "OPENPRC": "60.57", "PRC": "60.31", "BIDLO": "59.84", "ASKHI": "60.61"}, {"data": "2012/04/17", "OPENPRC": "60.74", "PRC": "61.54", "BIDLO": "60.602", "ASKHI": "61.7"}, {"data": "2012/04/18", "OPENPRC": "61.5", "PRC": "61.425", "BIDLO": "61.04", "ASKHI": "61.82"}, {"data": "2012/04/19", "OPENPRC": "61.3", "PRC": "60.9", "BIDLO": "60.41", "ASKHI": "61.78"}, {"data": "2012/04/20", "OPENPRC": "57.89", "PRC": "57.25", "BIDLO": "55.96", "ASKHI": "58.99"}, {"data": "2012/04/23", "OPENPRC": "56.71", "PRC": "56.75", "BIDLO": "56.1", "ASKHI": "56.88"}, {"data": "2012/04/24", "OPENPRC": "56.69", "PRC": "56.29", "BIDLO": "56.075", "ASKHI": "56.761"}, {"data": "2012/04/25", "OPENPRC": "56.92", "PRC": "57.4", "BIDLO": "56.668", "ASKHI": "57.77"}, {"data": "2012/04/26", "OPENPRC": "57.3", "PRC": "57.6", "BIDLO": "57.16", "ASKHI": "57.81"}, {"data": "2012/04/27", "OPENPRC": "57.66", "PRC": "57.98", "BIDLO": "57.65", "ASKHI": "58.22"}, {"data": "2012/04/30", "OPENPRC": "57.92", "PRC": "57.97", "BIDLO": "57.55", "ASKHI": "58.18"}, {"data": "2012/05/01", "OPENPRC": "58.12", "PRC": "58.25", "BIDLO": "57.8", "ASKHI": "58.87"}, {"data": "2012/05/02", "OPENPRC": "57.83", "PRC": "58.64", "BIDLO": "57.24", "ASKHI": "58.71"}, {"data": "2012/05/03", "OPENPRC": "58.79", "PRC": "58.39", "BIDLO": "58.18", "ASKHI": "59.0"}, {"data": "2012/05/04", "OPENPRC": "57.67", "PRC": "56.9", "BIDLO": "56.695", "ASKHI": "57.9"}, {"data": "2012/05/07", "OPENPRC": "56.42", "PRC": "56.58", "BIDLO": "56.13", "ASKHI": "56.83"}, {"data": "2012/05/08", "OPENPRC": "56.24", "PRC": "56.28", "BIDLO": "55.46", "ASKHI": "56.48"}, {"data": "2012/05/09", "OPENPRC": "55.87", "PRC": "56.52", "BIDLO": "55.41", "ASKHI": "56.93"}, {"data": "2012/05/10", "OPENPRC": "56.82", "PRC": "55.43", "BIDLO": "55.12", "ASKHI": "56.91"}, {"data": "2012/05/11", "OPENPRC": "55.4", "PRC": "55.83", "BIDLO": "55.13", "ASKHI": "56.23"}, {"data": "2012/05/14", "OPENPRC": "55.28", "PRC": "55.35", "BIDLO": "55.06", "ASKHI": "55.84"}, {"data": "2012/05/15", "OPENPRC": "55.4", "PRC": "55.49", "BIDLO": "55.31", "ASKHI": "56.47"}, {"data": "2012/05/16", "OPENPRC": "55.66", "PRC": "55.1", "BIDLO": "55.1", "ASKHI": "56.11"}, {"data": "2012/05/17", "OPENPRC": "55.0", "PRC": "54.41", "BIDLO": "54.21", "ASKHI": "55.29"}, {"data": "2012/05/18", "OPENPRC": "54.52", "PRC": "54.51", "BIDLO": "53.38", "ASKHI": "56.9"}, {"data": "2012/05/21", "OPENPRC": "54.55", "PRC": "55.25", "BIDLO": "53.49", "ASKHI": "55.39"}, {"data": "2012/05/22", "OPENPRC": "55.39", "PRC": "55.99", "BIDLO": "55.0717", "ASKHI": "56.36"}, {"data": "2012/05/23", "OPENPRC": "55.75", "PRC": "56.47", "BIDLO": "55.24", "ASKHI": "56.63"}, {"data": "2012/05/24", "OPENPRC": "56.52", "PRC": "56.39", "BIDLO": "55.81", "ASKHI": "56.52"}, {"data": "2012/05/25", "OPENPRC": "56.5", "PRC": "56.45", "BIDLO": "56.13", "ASKHI": "56.755"}, {"data": "2012/05/29", "OPENPRC": "56.5", "PRC": "56.63", "BIDLO": "56.26", "ASKHI": "57.2"}, {"data": "2012/05/30", "OPENPRC": "56.25", "PRC": "56.2", "BIDLO": "55.62", "ASKHI": "56.41"}, {"data": "2012/05/31", "OPENPRC": "56.38", "PRC": "56.23", "BIDLO": "55.76", "ASKHI": "56.72"}, {"data": "2012/06/01", "OPENPRC": "55.14", "PRC": "54.8", "BIDLO": "54.77", "ASKHI": "55.59"}, {"data": "2012/06/04", "OPENPRC": "55.28", "PRC": "54.92", "BIDLO": "54.3", "ASKHI": "55.6"}, {"data": "2012/06/05", "OPENPRC": "54.7", "PRC": "55.66", "BIDLO": "54.69", "ASKHI": "55.73"}, {"data": "2012/06/06", "OPENPRC": "56.0", "PRC": "57.695", "BIDLO": "55.7212", "ASKHI": "57.72"}, {"data": "2012/06/07", "OPENPRC": "58.09", "PRC": "56.94", "BIDLO": "56.94", "ASKHI": "58.2"}, {"data": "2012/06/08", "OPENPRC": "56.92", "PRC": "57.0", "BIDLO": "56.5", "ASKHI": "57.11"}, {"data": "2012/06/11", "OPENPRC": "57.12", "PRC": "55.43", "BIDLO": "55.37", "ASKHI": "57.38"}, {"data": "2012/06/12", "OPENPRC": "55.76", "PRC": "56.77", "BIDLO": "55.46", "ASKHI": "56.77"}, {"data": "2012/06/13", "OPENPRC": "56.57", "PRC": "56.475", "BIDLO": "56.39", "ASKHI": "57.32"}, {"data": "2012/06/14", "OPENPRC": "56.61", "PRC": "57.37", "BIDLO": "56.24", "ASKHI": "57.52"}, {"data": "2012/06/15", "OPENPRC": "57.34", "PRC": "58.32", "BIDLO": "57.16", "ASKHI": "58.39"}, {"data": "2012/06/18", "OPENPRC": "58.07", "PRC": "58.7", "BIDLO": "57.77", "ASKHI": "58.89"}, {"data": "2012/06/19", "OPENPRC": "59.0", "PRC": "58.97", "BIDLO": "58.49", "ASKHI": "59.0"}, {"data": "2012/06/20", "OPENPRC": "59.0", "PRC": "58.83", "BIDLO": "58.36", "ASKHI": "59.17"}, {"data": "2012/06/21", "OPENPRC": "58.82", "PRC": "56.89", "BIDLO": "56.84", "ASKHI": "58.92"}, {"data": "2012/06/22", "OPENPRC": "57.11", "PRC": "57.66", "BIDLO": "56.84", "ASKHI": "57.76"}, {"data": "2012/06/25", "OPENPRC": "57.01", "PRC": "56.35", "BIDLO": "56.2", "ASKHI": "57.25"}, {"data": "2012/06/26", "OPENPRC": "56.67", "PRC": "57.01", "BIDLO": "56.44", "ASKHI": "57.27"}, {"data": "2012/06/27", "OPENPRC": "57.4", "PRC": "57.52", "BIDLO": "57.09", "ASKHI": "57.85"}, {"data": "2012/06/28", "OPENPRC": "57.32", "PRC": "57.0", "BIDLO": "56.19", "ASKHI": "57.35"}, {"data": "2012/06/29", "OPENPRC": "57.73", "PRC": "59.35", "BIDLO": "57.73", "ASKHI": "59.36"}, {"data": "2012/07/02", "OPENPRC": "59.29", "PRC": "59.68", "BIDLO": "59.15", "ASKHI": "59.91"}, {"data": "2012/07/03", "OPENPRC": "59.62", "PRC": "60.15", "BIDLO": "59.5899", "ASKHI": "60.21"}, {"data": "2012/07/05", "OPENPRC": "59.07", "PRC": "59.92", "BIDLO": "59.03", "ASKHI": "60.06"}, {"data": "2012/07/06", "OPENPRC": "59.47", "PRC": "57.9", "BIDLO": "57.38", "ASKHI": "59.77"}, {"data": "2012/07/09", "OPENPRC": "57.99", "PRC": "57.44", "BIDLO": "56.81", "ASKHI": "58.18"}, {"data": "2012/07/10", "OPENPRC": "57.9", "PRC": "57.45", "BIDLO": "56.92", "ASKHI": "58.21"}, {"data": "2012/07/11", "OPENPRC": "57.45", "PRC": "57.34", "BIDLO": "56.78", "ASKHI": "57.74"}, {"data": "2012/07/12", "OPENPRC": "56.84", "PRC": "56.62", "BIDLO": "55.85", "ASKHI": "56.97"}, {"data": "2012/07/13", "OPENPRC": "56.65", "PRC": "57.22", "BIDLO": "56.52", "ASKHI": "57.45"}, {"data": "2012/07/16", "OPENPRC": "57.2", "PRC": "57.13", "BIDLO": "56.58", "ASKHI": "57.53"}, {"data": "2012/07/17", "OPENPRC": "57.56", "PRC": "58.17", "BIDLO": "56.74", "ASKHI": "58.37"}, {"data": "2012/07/18", "OPENPRC": "57.96", "PRC": "59.76", "BIDLO": "57.96", "ASKHI": "59.78"}, {"data": "2012/07/19", "OPENPRC": "59.69", "PRC": "59.62", "BIDLO": "59.44", "ASKHI": "60.0"}, {"data": "2012/07/20", "OPENPRC": "59.59", "PRC": "58.69", "BIDLO": "58.49", "ASKHI": "59.75"}, {"data": "2012/07/23", "OPENPRC": "57.54", "PRC": "57.09", "BIDLO": "56.61", "ASKHI": "57.54"}, {"data": "2012/07/24", "OPENPRC": "57.01", "PRC": "56.76", "BIDLO": "56.45", "ASKHI": "57.09"}, {"data": "2012/07/25", "OPENPRC": "56.8", "PRC": "56.52", "BIDLO": "56.31", "ASKHI": "57.41"}, {"data": "2012/07/26", "OPENPRC": "57.51", "PRC": "57.31", "BIDLO": "56.9", "ASKHI": "58.25"}, {"data": "2012/07/27", "OPENPRC": "57.75", "PRC": "58.88", "BIDLO": "57.73", "ASKHI": "59.08"}, {"data": "2012/07/30", "OPENPRC": "58.88", "PRC": "58.51", "BIDLO": "58.25", "ASKHI": "59.14"}, {"data": "2012/07/31", "OPENPRC": "58.45", "PRC": "58.02", "BIDLO": "57.88", "ASKHI": "58.71"}, {"data": "2012/08/01", "OPENPRC": "58.12", "PRC": "57.93", "BIDLO": "57.83", "ASKHI": "58.39"}, {"data": "2012/08/02", "OPENPRC": "57.52", "PRC": "57.79", "BIDLO": "57.17", "ASKHI": "58.17"}, {"data": "2012/08/03", "OPENPRC": "57.67", "PRC": "59.07", "BIDLO": "57.09", "ASKHI": "59.16"}, {"data": "2012/08/06", "OPENPRC": "59.15", "PRC": "59.62", "BIDLO": "58.93", "ASKHI": "59.88"}, {"data": "2012/08/07", "OPENPRC": "59.95", "PRC": "59.77", "BIDLO": "59.72", "ASKHI": "60.3"}, {"data": "2012/08/08", "OPENPRC": "59.86", "PRC": "59.62", "BIDLO": "59.11", "ASKHI": "60.2"}, {"data": "2012/08/09", "OPENPRC": "59.67", "PRC": "59.1", "BIDLO": "58.96", "ASKHI": "59.75"}, {"data": "2012/08/10", "OPENPRC": "59.06", "PRC": "59.03", "BIDLO": "58.74", "ASKHI": "59.27"}, {"data": "2012/08/13", "OPENPRC": "58.7", "PRC": "58.295", "BIDLO": "58.26", "ASKHI": "58.98"}, {"data": "2012/08/14", "OPENPRC": "58.68", "PRC": "58.02", "BIDLO": "57.85", "ASKHI": "58.72"}, {"data": "2012/08/15", "OPENPRC": "58.16", "PRC": "59.2", "BIDLO": "57.94", "ASKHI": "59.32"}, {"data": "2012/08/16", "OPENPRC": "59.21", "PRC": "60.07", "BIDLO": "59.15", "ASKHI": "60.19"}, {"data": "2012/08/17", "OPENPRC": "60.1", "PRC": "59.76", "BIDLO": "59.55", "ASKHI": "60.41"}, {"data": "2012/08/20", "OPENPRC": "59.57", "PRC": "59.35", "BIDLO": "59.13", "ASKHI": "59.9"}, {"data": "2012/08/21", "OPENPRC": "59.61", "PRC": "58.95", "BIDLO": "58.71", "ASKHI": "59.84"}, {"data": "2012/08/22", "OPENPRC": "58.91", "PRC": "59.65", "BIDLO": "57.925", "ASKHI": "59.93"}, {"data": "2012/08/23", "OPENPRC": "59.05", "PRC": "58.19", "BIDLO": "57.84", "ASKHI": "59.19"}, {"data": "2012/08/24", "OPENPRC": "58.26", "PRC": "58.43", "BIDLO": "57.925", "ASKHI": "58.58"}, {"data": "2012/08/27", "OPENPRC": "58.3", "PRC": "58.93", "BIDLO": "58.25", "ASKHI": "59.35"}, {"data": "2012/08/28", "OPENPRC": "58.81", "PRC": "58.78", "BIDLO": "58.58", "ASKHI": "59.16"}, {"data": "2012/08/29", "OPENPRC": "58.8", "PRC": "59.01", "BIDLO": "58.735", "ASKHI": "59.09"}, {"data": "2012/08/30", "OPENPRC": "58.57", "PRC": "58.21", "BIDLO": "58.02", "ASKHI": "58.75"}, {"data": "2012/08/31", "OPENPRC": "58.79", "PRC": "58.54", "BIDLO": "57.95", "ASKHI": "59.02"}, {"data": "2012/09/04", "OPENPRC": "58.4", "PRC": "58.55", "BIDLO": "58.03", "ASKHI": "58.83"}, {"data": "2012/09/05", "OPENPRC": "58.71", "PRC": "58.29", "BIDLO": "58.01", "ASKHI": "58.71"}, {"data": "2012/09/06", "OPENPRC": "58.52", "PRC": "59.74", "BIDLO": "58.49", "ASKHI": "59.76"}, {"data": "2012/09/07", "OPENPRC": "59.48", "PRC": "59.46", "BIDLO": "59.31", "ASKHI": "59.86"}, {"data": "2012/09/10", "OPENPRC": "59.47", "PRC": "59.62", "BIDLO": "59.35", "ASKHI": "59.9"}, {"data": "2012/09/11", "OPENPRC": "59.3", "PRC": "59.95", "BIDLO": "59.11", "ASKHI": "60.1801"}, {"data": "2012/09/12", "OPENPRC": "59.99", "PRC": "59.92", "BIDLO": "59.64", "ASKHI": "60.16"}, {"data": "2012/09/13", "OPENPRC": "59.79", "PRC": "59.97", "BIDLO": "59.56", "ASKHI": "60.4"}, {"data": "2012/09/14", "OPENPRC": "59.97", "PRC": "60.28", "BIDLO": "59.79", "ASKHI": "60.79"}, {"data": "2012/09/17", "OPENPRC": "60.1", "PRC": "60.15", "BIDLO": "59.7", "ASKHI": "60.39"}, {"data": "2012/09/18", "OPENPRC": "60.15", "PRC": "59.36", "BIDLO": "59.31", "ASKHI": "60.495"}, {"data": "2012/09/19", "OPENPRC": "59.58", "PRC": "58.63", "BIDLO": "58.34", "ASKHI": "59.63"}, {"data": "2012/09/20", "OPENPRC": "58.2", "PRC": "58.82", "BIDLO": "58.19", "ASKHI": "58.85"}, {"data": "2012/09/21", "OPENPRC": "59.04", "PRC": "58.38", "BIDLO": "58.2", "ASKHI": "59.12"}, {"data": "2012/09/24", "OPENPRC": "58.72", "PRC": "58.17", "BIDLO": "57.92", "ASKHI": "58.72"}, {"data": "2012/09/25", "OPENPRC": "58.48", "PRC": "57.87", "BIDLO": "57.8", "ASKHI": "58.5"}, {"data": "2012/09/26", "OPENPRC": "57.79", "PRC": "57.97", "BIDLO": "57.55", "ASKHI": "58.03"}, {"data": "2012/09/27", "OPENPRC": "58.16", "PRC": "58.835", "BIDLO": "57.83", "ASKHI": "58.93"}, {"data": "2012/09/28", "OPENPRC": "58.49", "PRC": "58.88", "BIDLO": "58.38", "ASKHI": "58.95"}, {"data": "2012/10/01", "OPENPRC": "59.12", "PRC": "59.335", "BIDLO": "58.695", "ASKHI": "59.36"}, {"data": "2012/10/02", "OPENPRC": "59.54", "PRC": "59.85", "BIDLO": "59.255", "ASKHI": "59.89"}, {"data": "2012/10/03", "OPENPRC": "59.99", "PRC": "61.065", "BIDLO": "59.87", "ASKHI": "61.29"}, {"data": "2012/10/04", "OPENPRC": "61.05", "PRC": "61.07", "BIDLO": "60.61", "ASKHI": "61.18"}, {"data": "2012/10/05", "OPENPRC": "61.42", "PRC": "61.12", "BIDLO": "60.93", "ASKHI": "61.7"}, {"data": "2012/10/08", "OPENPRC": "60.75", "PRC": "60.57", "BIDLO": "60.45", "ASKHI": "60.95"}, {"data": "2012/10/09", "OPENPRC": "60.48", "PRC": "59.86", "BIDLO": "59.83", "ASKHI": "60.61"}, {"data": "2012/10/10", "OPENPRC": "60.03", "PRC": "59.64", "BIDLO": "59.3", "ASKHI": "60.03"}, {"data": "2012/10/11", "OPENPRC": "60.2", "PRC": "59.62", "BIDLO": "59.47", "ASKHI": "60.29"}, {"data": "2012/10/12", "OPENPRC": "59.84", "PRC": "59.8895", "BIDLO": "59.62", "ASKHI": "60.26"}, {"data": "2012/10/15", "OPENPRC": "59.91", "PRC": "60.11", "BIDLO": "59.63", "ASKHI": "60.18"}, {"data": "2012/10/16", "OPENPRC": "60.32", "PRC": "60.79", "BIDLO": "60.12", "ASKHI": "61.15"}, {"data": "2012/10/17", "OPENPRC": "60.42", "PRC": "60.91", "BIDLO": "60.42", "ASKHI": "61.225"}, {"data": "2012/10/18", "OPENPRC": "60.85", "PRC": "60.62", "BIDLO": "60.46", "ASKHI": "61.14"}, {"data": "2012/10/19", "OPENPRC": "60.79", "PRC": "59.82", "BIDLO": "59.69", "ASKHI": "61.09"}, {"data": "2012/10/22", "OPENPRC": "59.84", "PRC": "59.94", "BIDLO": "59.46", "ASKHI": "60.04"}, {"data": "2012/10/23", "OPENPRC": "59.25", "PRC": "59.575", "BIDLO": "58.97", "ASKHI": "59.8"}, {"data": "2012/10/24", "OPENPRC": "59.86", "PRC": "59.6", "BIDLO": "59.53", "ASKHI": "59.89"}, {"data": "2012/10/25", "OPENPRC": "59.98", "PRC": "59.44", "BIDLO": "59.38", "ASKHI": "60.08"}, {"data": "2012/10/26", "OPENPRC": "59.35", "PRC": "59.39", "BIDLO": "58.86", "ASKHI": "59.62"}, {"data": "2012/10/31", "OPENPRC": "59.58", "PRC": "59.43", "BIDLO": "59.04", "ASKHI": "59.75"}, {"data": "2012/11/01", "OPENPRC": "59.7", "PRC": "61.43", "BIDLO": "59.46", "ASKHI": "61.48"}, {"data": "2012/11/02", "OPENPRC": "61.5", "PRC": "61.19", "BIDLO": "60.69", "ASKHI": "61.62"}, {"data": "2012/11/05", "OPENPRC": "61.06", "PRC": "60.94", "BIDLO": "60.63", "ASKHI": "61.12"}, {"data": "2012/11/06", "OPENPRC": "61.25", "PRC": "61.78", "BIDLO": "60.761", "ASKHI": "62.1"}, {"data": "2012/11/07", "OPENPRC": "61.14", "PRC": "60.53", "BIDLO": "60.3", "ASKHI": "61.56"}, {"data": "2012/11/08", "OPENPRC": "60.27", "PRC": "59.82", "BIDLO": "59.82", "ASKHI": "60.59"}, {"data": "2012/11/09", "OPENPRC": "59.92", "PRC": "59.96", "BIDLO": "59.43", "ASKHI": "60.48"}, {"data": "2012/11/12", "OPENPRC": "60.04", "PRC": "59.35", "BIDLO": "59.34", "ASKHI": "60.45"}, {"data": "2012/11/13", "OPENPRC": "58.97", "PRC": "59.23", "BIDLO": "58.96", "ASKHI": "59.79"}, {"data": "2012/11/14", "OPENPRC": "59.46", "PRC": "58.47", "BIDLO": "58.4", "ASKHI": "59.84"}, {"data": "2012/11/15", "OPENPRC": "58.46", "PRC": "58.77", "BIDLO": "58.41", "ASKHI": "59.42"}, {"data": "2012/11/16", "OPENPRC": "58.71", "PRC": "59.28", "BIDLO": "57.6", "ASKHI": "59.43"}, {"data": "2012/11/19", "OPENPRC": "59.82", "PRC": "58.95", "BIDLO": "58.52", "ASKHI": "59.89"}, {"data": "2012/11/20", "OPENPRC": "58.9", "PRC": "58.17", "BIDLO": "57.926", "ASKHI": "58.9"}, {"data": "2012/11/21", "OPENPRC": "58.33", "PRC": "58.56", "BIDLO": "58.26", "ASKHI": "58.97"}, {"data": "2012/11/23", "OPENPRC": "58.9", "PRC": "59.16", "BIDLO": "58.79", "ASKHI": "59.37"}, {"data": "2012/11/26", "OPENPRC": "58.8", "PRC": "58.43", "BIDLO": "58.16", "ASKHI": "58.99"}, {"data": "2012/11/27", "OPENPRC": "58.48", "PRC": "58.2", "BIDLO": "57.89", "ASKHI": "58.54"}, {"data": "2012/11/28", "OPENPRC": "58.03", "PRC": "58.58", "BIDLO": "57.84", "ASKHI": "58.59"}, {"data": "2012/11/29", "OPENPRC": "58.84", "PRC": "59.178", "BIDLO": "58.748", "ASKHI": "59.45"}, {"data": "2012/11/30", "OPENPRC": "59.2", "PRC": "59.91", "BIDLO": "59.14", "ASKHI": "59.965"}, {"data": "2012/12/03", "OPENPRC": "60.0", "PRC": "59.42", "BIDLO": "59.21", "ASKHI": "60.23"}, {"data": "2012/12/04", "OPENPRC": "59.47", "PRC": "59.725", "BIDLO": "59.1", "ASKHI": "59.85"}, {"data": "2012/12/05", "OPENPRC": "59.7", "PRC": "59.91", "BIDLO": "59.06", "ASKHI": "60.29"}, {"data": "2012/12/06", "OPENPRC": "59.79", "PRC": "59.73", "BIDLO": "59.29", "ASKHI": "60.25"}, {"data": "2012/12/07", "OPENPRC": "59.91", "PRC": "59.56", "BIDLO": "59.2", "ASKHI": "60.0"}, {"data": "2012/12/10", "OPENPRC": "59.64", "PRC": "59.61", "BIDLO": "59.47", "ASKHI": "60.0"}, {"data": "2012/12/11", "OPENPRC": "59.8", "PRC": "60.44", "BIDLO": "59.69", "ASKHI": "60.71"}, {"data": "2012/12/12", "OPENPRC": "60.43", "PRC": "60.2801", "BIDLO": "60.125", "ASKHI": "61.09"}, {"data": "2012/12/13", "OPENPRC": "60.37", "PRC": "60.06", "BIDLO": "59.614", "ASKHI": "60.57"}, {"data": "2012/12/14", "OPENPRC": "59.9", "PRC": "60.18", "BIDLO": "59.68", "ASKHI": "60.39"}, {"data": "2012/12/17", "OPENPRC": "60.23", "PRC": "61.17", "BIDLO": "60.04", "ASKHI": "61.23"}, {"data": "2012/12/18", "OPENPRC": "61.21", "PRC": "62.01", "BIDLO": "61.19", "ASKHI": "62.1"}, {"data": "2012/12/19", "OPENPRC": "62.11", "PRC": "62.13", "BIDLO": "62.01", "ASKHI": "62.86"}, {"data": "2012/12/20", "OPENPRC": "61.97", "PRC": "62.05", "BIDLO": "61.44", "ASKHI": "62.13"}, {"data": "2012/12/21", "OPENPRC": "61.64", "PRC": "61.44", "BIDLO": "61.0", "ASKHI": "61.97"}, {"data": "2012/12/24", "OPENPRC": "61.14", "PRC": "61.29", "BIDLO": "60.74", "ASKHI": "61.34"}, {"data": "2012/12/26", "OPENPRC": "61.1", "PRC": "60.87", "BIDLO": "60.68", "ASKHI": "61.49"}, {"data": "2012/12/27", "OPENPRC": "60.84", "PRC": "60.34", "BIDLO": "59.63", "ASKHI": "60.96"}, {"data": "2012/12/28", "OPENPRC": "59.94", "PRC": "59.33", "BIDLO": "59.33", "ASKHI": "60.24"}, {"data": "2012/12/31", "OPENPRC": "59.09", "PRC": "59.4754", "BIDLO": "58.76", "ASKHI": "59.67"}]