[{"data": "2012/01/03", "OPENPRC": "88.01", "PRC": "87.42", "BIDLO": "86.79", "ASKHI": "88.13"}, {"data": "2012/01/04", "OPENPRC": "87.46", "PRC": "87.35", "BIDLO": "86.73", "ASKHI": "87.76"}, {"data": "2012/01/05", "OPENPRC": "87.02", "PRC": "87.44", "BIDLO": "86.86", "ASKHI": "88.06"}, {"data": "2012/01/06", "OPENPRC": "87.45", "PRC": "87.21", "BIDLO": "86.769", "ASKHI": "87.5086"}, {"data": "2012/01/09", "OPENPRC": "87.23", "PRC": "86.76", "BIDLO": "86.33", "ASKHI": "87.4"}, {"data": "2012/01/10", "OPENPRC": "87.52", "PRC": "88.16", "BIDLO": "87.12", "ASKHI": "88.38"}, {"data": "2012/01/11", "OPENPRC": "88.16", "PRC": "88.36", "BIDLO": "87.83", "ASKHI": "88.57"}, {"data": "2012/01/12", "OPENPRC": "88.37", "PRC": "87.65", "BIDLO": "87.63", "ASKHI": "88.91"}, {"data": "2012/01/13", "OPENPRC": "87.02", "PRC": "88.81", "BIDLO": "87.01", "ASKHI": "88.95"}, {"data": "2012/01/17", "OPENPRC": "89.3", "PRC": "88.02", "BIDLO": "87.72", "ASKHI": "89.63"}, {"data": "2012/01/18", "OPENPRC": "88.08", "PRC": "88.74", "BIDLO": "87.9", "ASKHI": "89.21"}, {"data": "2012/01/19", "OPENPRC": "88.9", "PRC": "88.48", "BIDLO": "88.25", "ASKHI": "89.3368"}, {"data": "2012/01/20", "OPENPRC": "88.52", "PRC": "87.92", "BIDLO": "87.56", "ASKHI": "88.85"}, {"data": "2012/01/23", "OPENPRC": "87.81", "PRC": "87.93", "BIDLO": "87.74", "ASKHI": "88.97"}, {"data": "2012/01/24", "OPENPRC": "87.57", "PRC": "87.25", "BIDLO": "87.11", "ASKHI": "88.09"}, {"data": "2012/01/25", "OPENPRC": "86.86", "PRC": "87.65", "BIDLO": "86.26", "ASKHI": "87.88"}, {"data": "2012/01/26", "OPENPRC": "87.75", "PRC": "88.02", "BIDLO": "87.64", "ASKHI": "88.46"}, {"data": "2012/01/27", "OPENPRC": "87.5", "PRC": "85.1", "BIDLO": "85.08", "ASKHI": "87.5"}, {"data": "2012/01/30", "OPENPRC": "84.41", "PRC": "83.64", "BIDLO": "83.35", "ASKHI": "84.62"}, {"data": "2012/01/31", "OPENPRC": "83.8", "PRC": "83.16", "BIDLO": "82.81", "ASKHI": "83.92"}, {"data": "2012/02/01", "OPENPRC": "81.62", "PRC": "81.73", "BIDLO": "81.56", "ASKHI": "82.56"}, {"data": "2012/02/02", "OPENPRC": "81.89", "PRC": "80.9", "BIDLO": "80.59", "ASKHI": "82.31"}, {"data": "2012/02/03", "OPENPRC": "80.52", "PRC": "81.7", "BIDLO": "80.11", "ASKHI": "81.82"}, {"data": "2012/02/06", "OPENPRC": "81.24", "PRC": "81.73", "BIDLO": "81.04", "ASKHI": "81.86"}, {"data": "2012/02/07", "OPENPRC": "81.36", "PRC": "82.56", "BIDLO": "81.12", "ASKHI": "82.77"}, {"data": "2012/02/08", "OPENPRC": "82.59", "PRC": "81.95", "BIDLO": "81.53", "ASKHI": "82.73"}, {"data": "2012/02/09", "OPENPRC": "81.95", "PRC": "81.71", "BIDLO": "81.22", "ASKHI": "82.23"}, {"data": "2012/02/10", "OPENPRC": "81.23", "PRC": "81.01", "BIDLO": "80.63", "ASKHI": "81.33"}, {"data": "2012/02/13", "OPENPRC": "81.31", "PRC": "81.55", "BIDLO": "81.19", "ASKHI": "81.88"}, {"data": "2012/02/14", "OPENPRC": "81.55", "PRC": "81.27", "BIDLO": "80.87", "ASKHI": "81.75"}, {"data": "2012/02/15", "OPENPRC": "81.38", "PRC": "80.45", "BIDLO": "80.22", "ASKHI": "81.46"}, {"data": "2012/02/16", "OPENPRC": "80.75", "PRC": "82.37", "BIDLO": "80.74", "ASKHI": "82.67"}, {"data": "2012/02/17", "OPENPRC": "83.05", "PRC": "82.09", "BIDLO": "82.07", "ASKHI": "84.19"}, {"data": "2012/02/21", "OPENPRC": "82.43", "PRC": "83.26", "BIDLO": "82.28", "ASKHI": "83.38"}, {"data": "2012/02/22", "OPENPRC": "82.69", "PRC": "83.34", "BIDLO": "82.69", "ASKHI": "84.04"}, {"data": "2012/02/23", "OPENPRC": "83.41", "PRC": "84.16", "BIDLO": "83.41", "ASKHI": "84.28"}, {"data": "2012/02/24", "OPENPRC": "84.27", "PRC": "83.87", "BIDLO": "83.7099", "ASKHI": "84.42"}, {"data": "2012/02/27", "OPENPRC": "83.31", "PRC": "83.34", "BIDLO": "83.17", "ASKHI": "83.77"}, {"data": "2012/02/28", "OPENPRC": "83.29", "PRC": "82.08", "BIDLO": "81.61", "ASKHI": "83.39"}, {"data": "2012/02/29", "OPENPRC": "82.32", "PRC": "82.64", "BIDLO": "81.84", "ASKHI": "82.94"}, {"data": "2012/03/01", "OPENPRC": "82.67", "PRC": "82.6", "BIDLO": "82.12", "ASKHI": "83.01"}, {"data": "2012/03/02", "OPENPRC": "82.59", "PRC": "82.79", "BIDLO": "82.46", "ASKHI": "83.19"}, {"data": "2012/03/05", "OPENPRC": "82.49", "PRC": "83.12", "BIDLO": "82.33", "ASKHI": "83.2854"}, {"data": "2012/03/06", "OPENPRC": "82.64", "PRC": "82.54", "BIDLO": "82.11", "ASKHI": "82.81"}, {"data": "2012/03/07", "OPENPRC": "82.57", "PRC": "82.32", "BIDLO": "82.05", "ASKHI": "82.6"}, {"data": "2012/03/08", "OPENPRC": "82.64", "PRC": "82.6", "BIDLO": "82.25", "ASKHI": "83.01"}, {"data": "2012/03/09", "OPENPRC": "82.73", "PRC": "83.26", "BIDLO": "82.61", "ASKHI": "83.85"}, {"data": "2012/03/12", "OPENPRC": "83.64", "PRC": "84.49", "BIDLO": "83.64", "ASKHI": "85.01"}, {"data": "2012/03/13", "OPENPRC": "84.82", "PRC": "85.01", "BIDLO": "84.45", "ASKHI": "85.18"}, {"data": "2012/03/14", "OPENPRC": "85.0", "PRC": "83.91", "BIDLO": "83.88", "ASKHI": "85.28"}, {"data": "2012/03/15", "OPENPRC": "83.93", "PRC": "83.57", "BIDLO": "83.24", "ASKHI": "84.12"}, {"data": "2012/03/16", "OPENPRC": "83.51", "PRC": "82.85", "BIDLO": "82.8475", "ASKHI": "83.67"}, {"data": "2012/03/19", "OPENPRC": "82.84", "PRC": "83.05", "BIDLO": "82.83", "ASKHI": "83.7501"}, {"data": "2012/03/20", "OPENPRC": "82.66", "PRC": "82.83", "BIDLO": "82.41", "ASKHI": "83.0"}, {"data": "2012/03/21", "OPENPRC": "82.74", "PRC": "82.28", "BIDLO": "82.28", "ASKHI": "82.86"}, {"data": "2012/03/22", "OPENPRC": "81.84", "PRC": "81.52", "BIDLO": "81.21", "ASKHI": "81.92"}, {"data": "2012/03/23", "OPENPRC": "81.55", "PRC": "82.18", "BIDLO": "81.4", "ASKHI": "82.455"}, {"data": "2012/03/26", "OPENPRC": "82.66", "PRC": "82.6", "BIDLO": "82.39", "ASKHI": "83.09"}, {"data": "2012/03/27", "OPENPRC": "82.56", "PRC": "82.39", "BIDLO": "82.16", "ASKHI": "82.7"}, {"data": "2012/03/28", "OPENPRC": "82.15", "PRC": "81.83", "BIDLO": "81.3", "ASKHI": "82.57"}, {"data": "2012/03/29", "OPENPRC": "81.23", "PRC": "81.89", "BIDLO": "80.68", "ASKHI": "81.99"}, {"data": "2012/03/30", "OPENPRC": "82.16", "PRC": "81.66", "BIDLO": "81.5", "ASKHI": "82.22"}, {"data": "2012/04/02", "OPENPRC": "81.36", "PRC": "81.61", "BIDLO": "81.06", "ASKHI": "82.14"}, {"data": "2012/04/03", "OPENPRC": "81.66", "PRC": "81.9", "BIDLO": "81.33", "ASKHI": "81.97"}, {"data": "2012/04/04", "OPENPRC": "81.29", "PRC": "80.95", "BIDLO": "80.9", "ASKHI": "81.47"}, {"data": "2012/04/05", "OPENPRC": "80.75", "PRC": "81.1", "BIDLO": "80.7", "ASKHI": "81.34"}, {"data": "2012/04/09", "OPENPRC": "80.29", "PRC": "80.68", "BIDLO": "80.16", "ASKHI": "81.05"}, {"data": "2012/04/10", "OPENPRC": "80.68", "PRC": "79.36", "BIDLO": "79.1274", "ASKHI": "80.82"}, {"data": "2012/04/11", "OPENPRC": "80.11", "PRC": "80.54", "BIDLO": "80.07", "ASKHI": "81.05"}, {"data": "2012/04/12", "OPENPRC": "80.57", "PRC": "80.47", "BIDLO": "79.98", "ASKHI": "80.84"}, {"data": "2012/04/13", "OPENPRC": "80.35", "PRC": "80.22", "BIDLO": "80.15", "ASKHI": "81.16"}, {"data": "2012/04/16", "OPENPRC": "80.54", "PRC": "80.0", "BIDLO": "79.66", "ASKHI": "80.55"}, {"data": "2012/04/17", "OPENPRC": "80.35", "PRC": "81.09", "BIDLO": "79.69", "ASKHI": "81.24"}, {"data": "2012/04/18", "OPENPRC": "80.79", "PRC": "80.93", "BIDLO": "80.655", "ASKHI": "81.221"}, {"data": "2012/04/19", "OPENPRC": "80.86", "PRC": "80.94", "BIDLO": "80.48", "ASKHI": "81.375"}, {"data": "2012/04/20", "OPENPRC": "81.14", "PRC": "82.83", "BIDLO": "81.14", "ASKHI": "83.31"}, {"data": "2012/04/23", "OPENPRC": "82.0", "PRC": "82.18", "BIDLO": "81.18", "ASKHI": "82.23"}, {"data": "2012/04/24", "OPENPRC": "82.12", "PRC": "82.69", "BIDLO": "82.05", "ASKHI": "82.69"}, {"data": "2012/04/25", "OPENPRC": "83.3", "PRC": "84.36", "BIDLO": "83.13", "ASKHI": "84.49"}, {"data": "2012/04/26", "OPENPRC": "84.01", "PRC": "84.96", "BIDLO": "83.45", "ASKHI": "85.2"}, {"data": "2012/04/27", "OPENPRC": "85.41", "PRC": "85.49", "BIDLO": "85.0", "ASKHI": "85.95"}, {"data": "2012/04/30", "OPENPRC": "85.43", "PRC": "85.89", "BIDLO": "85.26", "ASKHI": "86.46"}, {"data": "2012/05/01", "OPENPRC": "86.05", "PRC": "86.78", "BIDLO": "85.9", "ASKHI": "87.54"}, {"data": "2012/05/02", "OPENPRC": "86.0", "PRC": "86.6", "BIDLO": "85.22", "ASKHI": "87.67"}, {"data": "2012/05/03", "OPENPRC": "86.54", "PRC": "86.58", "BIDLO": "86.505", "ASKHI": "87.73"}, {"data": "2012/05/04", "OPENPRC": "86.04", "PRC": "86.62", "BIDLO": "86.01", "ASKHI": "86.92"}, {"data": "2012/05/07", "OPENPRC": "86.56", "PRC": "86.34", "BIDLO": "86.04", "ASKHI": "86.86"}, {"data": "2012/05/08", "OPENPRC": "85.9", "PRC": "85.8", "BIDLO": "85.1", "ASKHI": "86.28"}, {"data": "2012/05/09", "OPENPRC": "85.1", "PRC": "85.25", "BIDLO": "84.84", "ASKHI": "86.17"}, {"data": "2012/05/10", "OPENPRC": "85.84", "PRC": "86.72", "BIDLO": "85.63", "ASKHI": "87.04"}, {"data": "2012/05/11", "OPENPRC": "86.35", "PRC": "86.45", "BIDLO": "86.3", "ASKHI": "87.2"}, {"data": "2012/05/14", "OPENPRC": "85.79", "PRC": "84.61", "BIDLO": "84.37", "ASKHI": "86.0"}, {"data": "2012/05/15", "OPENPRC": "84.74", "PRC": "84.36", "BIDLO": "84.04", "ASKHI": "85.57"}, {"data": "2012/05/16", "OPENPRC": "84.57", "PRC": "84.26", "BIDLO": "84.1", "ASKHI": "84.91"}, {"data": "2012/05/17", "OPENPRC": "84.21", "PRC": "82.17", "BIDLO": "82.17", "ASKHI": "84.4472"}, {"data": "2012/05/18", "OPENPRC": "82.33", "PRC": "81.57", "BIDLO": "81.1", "ASKHI": "83.16"}, {"data": "2012/05/21", "OPENPRC": "81.65", "PRC": "83.55", "BIDLO": "81.4", "ASKHI": "83.6049"}, {"data": "2012/05/22", "OPENPRC": "83.83", "PRC": "84.18", "BIDLO": "83.13", "ASKHI": "84.52"}, {"data": "2012/05/23", "OPENPRC": "83.9", "PRC": "82.81", "BIDLO": "81.9", "ASKHI": "83.9"}, {"data": "2012/05/24", "OPENPRC": "83.0", "PRC": "83.66", "BIDLO": "82.85", "ASKHI": "84.04"}, {"data": "2012/05/25", "OPENPRC": "83.79", "PRC": "83.6", "BIDLO": "83.32", "ASKHI": "83.95"}, {"data": "2012/05/29", "OPENPRC": "83.97", "PRC": "84.69", "BIDLO": "83.77", "ASKHI": "84.7"}, {"data": "2012/05/30", "OPENPRC": "83.98", "PRC": "83.21", "BIDLO": "83.18", "ASKHI": "84.87"}, {"data": "2012/05/31", "OPENPRC": "83.2", "PRC": "82.99", "BIDLO": "82.31", "ASKHI": "83.84"}, {"data": "2012/06/01", "OPENPRC": "81.94", "PRC": "79.8", "BIDLO": "79.63", "ASKHI": "82.29"}, {"data": "2012/06/04", "OPENPRC": "39.83", "PRC": "39.49", "BIDLO": "39.32", "ASKHI": "40.19"}, {"data": "2012/06/05", "OPENPRC": "39.54", "PRC": "40.16", "BIDLO": "39.33", "ASKHI": "40.22"}, {"data": "2012/06/06", "OPENPRC": "40.35", "PRC": "41.32", "BIDLO": "40.23", "ASKHI": "41.32"}, {"data": "2012/06/07", "OPENPRC": "41.97", "PRC": "41.32", "BIDLO": "41.17", "ASKHI": "42.06"}, {"data": "2012/06/08", "OPENPRC": "41.17", "PRC": "41.28", "BIDLO": "40.82", "ASKHI": "41.36"}, {"data": "2012/06/11", "OPENPRC": "41.51", "PRC": "41.19", "BIDLO": "41.12", "ASKHI": "41.69"}, {"data": "2012/06/12", "OPENPRC": "41.2", "PRC": "42.05", "BIDLO": "40.98", "ASKHI": "42.07"}, {"data": "2012/06/13", "OPENPRC": "41.97", "PRC": "42.04", "BIDLO": "41.84", "ASKHI": "42.299"}, {"data": "2012/06/14", "OPENPRC": "42.15", "PRC": "42.36", "BIDLO": "41.86", "ASKHI": "42.46"}, {"data": "2012/06/15", "OPENPRC": "42.69", "PRC": "42.91", "BIDLO": "42.42", "ASKHI": "43.16"}, {"data": "2012/06/18", "OPENPRC": "42.87", "PRC": "43.43", "BIDLO": "42.71", "ASKHI": "43.4901"}, {"data": "2012/06/19", "OPENPRC": "43.61", "PRC": "43.98", "BIDLO": "43.4", "ASKHI": "44.28"}, {"data": "2012/06/20", "OPENPRC": "43.92", "PRC": "43.53", "BIDLO": "43.3", "ASKHI": "44.6"}, {"data": "2012/06/21", "OPENPRC": "43.53", "PRC": "42.31", "BIDLO": "42.27", "ASKHI": "43.7"}, {"data": "2012/06/22", "OPENPRC": "42.47", "PRC": "42.59", "BIDLO": "42.05", "ASKHI": "42.66"}, {"data": "2012/06/25", "OPENPRC": "42.14", "PRC": "41.55", "BIDLO": "41.28", "ASKHI": "42.26"}, {"data": "2012/06/26", "OPENPRC": "41.57", "PRC": "41.24", "BIDLO": "40.93", "ASKHI": "41.72"}, {"data": "2012/06/27", "OPENPRC": "41.25", "PRC": "41.52", "BIDLO": "41.12", "ASKHI": "41.71"}, {"data": "2012/06/28", "OPENPRC": "41.3", "PRC": "41.55", "BIDLO": "40.87", "ASKHI": "41.57"}, {"data": "2012/06/29", "OPENPRC": "42.13", "PRC": "42.31", "BIDLO": "41.82", "ASKHI": "42.43"}, {"data": "2012/07/02", "OPENPRC": "42.58", "PRC": "42.73", "BIDLO": "42.03", "ASKHI": "42.73"}, {"data": "2012/07/03", "OPENPRC": "42.8", "PRC": "43.0", "BIDLO": "42.66", "ASKHI": "43.24"}, {"data": "2012/07/05", "OPENPRC": "42.75", "PRC": "42.91", "BIDLO": "42.65", "ASKHI": "43.14"}, {"data": "2012/07/06", "OPENPRC": "42.45", "PRC": "42.78", "BIDLO": "42.37", "ASKHI": "42.95"}, {"data": "2012/07/09", "OPENPRC": "42.6", "PRC": "42.6", "BIDLO": "42.41", "ASKHI": "42.69"}, {"data": "2012/07/10", "OPENPRC": "42.62", "PRC": "42.26", "BIDLO": "42.14", "ASKHI": "43.09"}, {"data": "2012/07/11", "OPENPRC": "42.28", "PRC": "42.33", "BIDLO": "42.05", "ASKHI": "42.6"}, {"data": "2012/07/12", "OPENPRC": "42.57", "PRC": "42.93", "BIDLO": "42.3701", "ASKHI": "43.11"}, {"data": "2012/07/13", "OPENPRC": "42.95", "PRC": "43.29", "BIDLO": "42.94", "ASKHI": "43.55"}, {"data": "2012/07/16", "OPENPRC": "43.17", "PRC": "43.41", "BIDLO": "43.08", "ASKHI": "43.74"}, {"data": "2012/07/17", "OPENPRC": "43.6", "PRC": "43.85", "BIDLO": "43.35", "ASKHI": "43.9"}, {"data": "2012/07/18", "OPENPRC": "43.62", "PRC": "44.0", "BIDLO": "43.62", "ASKHI": "44.11"}, {"data": "2012/07/19", "OPENPRC": "43.98", "PRC": "44.1", "BIDLO": "43.36", "ASKHI": "44.28"}, {"data": "2012/07/20", "OPENPRC": "43.78", "PRC": "44.06", "BIDLO": "43.78", "ASKHI": "44.42"}, {"data": "2012/07/23", "OPENPRC": "43.87", "PRC": "43.95", "BIDLO": "43.32", "ASKHI": "44.05"}, {"data": "2012/07/24", "OPENPRC": "43.9", "PRC": "43.36", "BIDLO": "42.8", "ASKHI": "43.99"}, {"data": "2012/07/25", "OPENPRC": "43.52", "PRC": "43.12", "BIDLO": "43.03", "ASKHI": "43.75"}, {"data": "2012/07/26", "OPENPRC": "43.86", "PRC": "43.6", "BIDLO": "43.44", "ASKHI": "44.05"}, {"data": "2012/07/27", "OPENPRC": "43.8", "PRC": "45.32", "BIDLO": "43.8", "ASKHI": "45.59"}, {"data": "2012/07/30", "OPENPRC": "45.25", "PRC": "45.35", "BIDLO": "45.21", "ASKHI": "45.94"}, {"data": "2012/07/31", "OPENPRC": "45.27", "PRC": "44.51", "BIDLO": "44.385", "ASKHI": "45.4"}, {"data": "2012/08/01", "OPENPRC": "44.24", "PRC": "44.68", "BIDLO": "41.92", "ASKHI": "46.07"}, {"data": "2012/08/02", "OPENPRC": "43.74", "PRC": "44.04", "BIDLO": "43.35", "ASKHI": "44.29"}, {"data": "2012/08/03", "OPENPRC": "44.76", "PRC": "44.72", "BIDLO": "44.543", "ASKHI": "44.825"}, {"data": "2012/08/06", "OPENPRC": "44.94", "PRC": "44.99", "BIDLO": "44.595", "ASKHI": "45.29"}, {"data": "2012/08/07", "OPENPRC": "45.2", "PRC": "44.83", "BIDLO": "44.76", "ASKHI": "45.49"}, {"data": "2012/08/08", "OPENPRC": "44.59", "PRC": "44.64", "BIDLO": "44.52", "ASKHI": "44.88"}, {"data": "2012/08/09", "OPENPRC": "44.47", "PRC": "44.65", "BIDLO": "44.44", "ASKHI": "44.84"}, {"data": "2012/08/10", "OPENPRC": "44.48", "PRC": "44.75", "BIDLO": "44.13", "ASKHI": "44.98"}, {"data": "2012/08/13", "OPENPRC": "44.64", "PRC": "44.44", "BIDLO": "44.33", "ASKHI": "44.9"}, {"data": "2012/08/14", "OPENPRC": "44.5", "PRC": "44.37", "BIDLO": "44.21", "ASKHI": "44.73"}, {"data": "2012/08/15", "OPENPRC": "44.45", "PRC": "44.37", "BIDLO": "44.21", "ASKHI": "44.65"}, {"data": "2012/08/16", "OPENPRC": "44.5", "PRC": "44.53", "BIDLO": "44.29", "ASKHI": "44.68"}, {"data": "2012/08/17", "OPENPRC": "44.66", "PRC": "44.3", "BIDLO": "43.985", "ASKHI": "44.83"}, {"data": "2012/08/20", "OPENPRC": "44.33", "PRC": "44.4", "BIDLO": "44.24", "ASKHI": "44.63"}, {"data": "2012/08/21", "OPENPRC": "44.41", "PRC": "44.5", "BIDLO": "44.36", "ASKHI": "44.98"}, {"data": "2012/08/22", "OPENPRC": "44.38", "PRC": "44.49", "BIDLO": "44.25", "ASKHI": "44.62"}, {"data": "2012/08/23", "OPENPRC": "44.35", "PRC": "44.33", "BIDLO": "44.18", "ASKHI": "44.49"}, {"data": "2012/08/24", "OPENPRC": "44.21", "PRC": "44.59", "BIDLO": "44.12", "ASKHI": "44.77"}, {"data": "2012/08/27", "OPENPRC": "44.56", "PRC": "44.67", "BIDLO": "44.44", "ASKHI": "44.86"}, {"data": "2012/08/28", "OPENPRC": "44.51", "PRC": "44.47", "BIDLO": "44.44", "ASKHI": "44.72"}, {"data": "2012/08/29", "OPENPRC": "44.54", "PRC": "44.75", "BIDLO": "44.41", "ASKHI": "44.99"}, {"data": "2012/08/30", "OPENPRC": "44.54", "PRC": "44.5", "BIDLO": "44.45", "ASKHI": "44.71"}, {"data": "2012/08/31", "OPENPRC": "44.78", "PRC": "44.53", "BIDLO": "44.26", "ASKHI": "44.85"}, {"data": "2012/09/04", "OPENPRC": "44.52", "PRC": "45.0", "BIDLO": "44.39", "ASKHI": "45.07"}, {"data": "2012/09/05", "OPENPRC": "45.11", "PRC": "44.88", "BIDLO": "44.78", "ASKHI": "45.11"}, {"data": "2012/09/06", "OPENPRC": "45.08", "PRC": "45.58", "BIDLO": "44.95", "ASKHI": "45.58"}, {"data": "2012/09/07", "OPENPRC": "45.6", "PRC": "45.75", "BIDLO": "45.48", "ASKHI": "45.8"}, {"data": "2012/09/10", "OPENPRC": "45.91", "PRC": "45.9", "BIDLO": "45.75", "ASKHI": "46.21"}, {"data": "2012/09/11", "OPENPRC": "45.97", "PRC": "46.15", "BIDLO": "45.78", "ASKHI": "46.15"}, {"data": "2012/09/12", "OPENPRC": "46.24", "PRC": "46.31", "BIDLO": "46.01", "ASKHI": "46.36"}, {"data": "2012/09/13", "OPENPRC": "46.29", "PRC": "46.96", "BIDLO": "46.18", "ASKHI": "47.04"}, {"data": "2012/09/14", "OPENPRC": "46.93", "PRC": "47.09", "BIDLO": "46.83", "ASKHI": "47.36"}, {"data": "2012/09/17", "OPENPRC": "46.92", "PRC": "46.98", "BIDLO": "46.83", "ASKHI": "47.12"}, {"data": "2012/09/18", "OPENPRC": "46.98", "PRC": "46.76", "BIDLO": "46.74", "ASKHI": "47.04"}, {"data": "2012/09/19", "OPENPRC": "46.79", "PRC": "46.91", "BIDLO": "46.65", "ASKHI": "47.05"}, {"data": "2012/09/20", "OPENPRC": "46.64", "PRC": "46.98", "BIDLO": "46.64", "ASKHI": "47.0"}, {"data": "2012/09/21", "OPENPRC": "47.25", "PRC": "47.11", "BIDLO": "47.09", "ASKHI": "47.5"}, {"data": "2012/09/24", "OPENPRC": "47.06", "PRC": "47.81", "BIDLO": "46.96", "ASKHI": "47.95"}, {"data": "2012/09/25", "OPENPRC": "48.41", "PRC": "47.11", "BIDLO": "47.1", "ASKHI": "49.36"}, {"data": "2012/09/26", "OPENPRC": "47.2", "PRC": "47.8", "BIDLO": "47.1677", "ASKHI": "48.1"}, {"data": "2012/09/27", "OPENPRC": "47.9", "PRC": "48.03", "BIDLO": "47.51", "ASKHI": "48.14"}, {"data": "2012/09/28", "OPENPRC": "47.82", "PRC": "48.31", "BIDLO": "47.69", "ASKHI": "48.41"}, {"data": "2012/10/01", "OPENPRC": "48.43", "PRC": "48.08", "BIDLO": "47.94", "ASKHI": "48.43"}, {"data": "2012/10/02", "OPENPRC": "48.24", "PRC": "48.1", "BIDLO": "47.8234", "ASKHI": "48.485"}, {"data": "2012/10/03", "OPENPRC": "48.19", "PRC": "48.83", "BIDLO": "48.14", "ASKHI": "48.84"}, {"data": "2012/10/04", "OPENPRC": "49.01", "PRC": "49.11", "BIDLO": "48.99", "ASKHI": "49.66"}, {"data": "2012/10/05", "OPENPRC": "49.3", "PRC": "49.39", "BIDLO": "49.16", "ASKHI": "49.79"}, {"data": "2012/10/08", "OPENPRC": "49.32", "PRC": "49.07", "BIDLO": "48.82", "ASKHI": "49.4"}, {"data": "2012/10/09", "OPENPRC": "49.1", "PRC": "48.68", "BIDLO": "48.59", "ASKHI": "49.43"}, {"data": "2012/10/10", "OPENPRC": "48.7", "PRC": "48.06", "BIDLO": "47.96", "ASKHI": "48.89"}, {"data": "2012/10/11", "OPENPRC": "48.37", "PRC": "47.95", "BIDLO": "47.94", "ASKHI": "48.37"}, {"data": "2012/10/12", "OPENPRC": "48.13", "PRC": "47.8", "BIDLO": "47.59", "ASKHI": "48.36"}, {"data": "2012/10/15", "OPENPRC": "47.78", "PRC": "47.84", "BIDLO": "47.3514", "ASKHI": "47.9"}, {"data": "2012/10/16", "OPENPRC": "48.0", "PRC": "48.28", "BIDLO": "47.86", "ASKHI": "48.31"}, {"data": "2012/10/17", "OPENPRC": "48.45", "PRC": "48.89", "BIDLO": "48.431", "ASKHI": "48.99"}, {"data": "2012/10/18", "OPENPRC": "48.85", "PRC": "48.41", "BIDLO": "48.27", "ASKHI": "48.88"}, {"data": "2012/10/19", "OPENPRC": "48.39", "PRC": "47.62", "BIDLO": "47.54", "ASKHI": "48.71"}, {"data": "2012/10/22", "OPENPRC": "47.39", "PRC": "47.15", "BIDLO": "47.01", "ASKHI": "47.79"}, {"data": "2012/10/23", "OPENPRC": "46.8", "PRC": "46.8", "BIDLO": "46.23", "ASKHI": "47.0561"}, {"data": "2012/10/24", "OPENPRC": "46.9", "PRC": "47.19", "BIDLO": "46.83", "ASKHI": "47.55"}, {"data": "2012/10/25", "OPENPRC": "47.38", "PRC": "47.25", "BIDLO": "46.98", "ASKHI": "47.7569"}, {"data": "2012/10/26", "OPENPRC": "47.2", "PRC": "47.14", "BIDLO": "46.84", "ASKHI": "47.3"}, {"data": "2012/10/31", "OPENPRC": "47.38", "PRC": "47.3", "BIDLO": "46.94", "ASKHI": "48.69"}, {"data": "2012/11/01", "OPENPRC": "47.28", "PRC": "46.77", "BIDLO": "46.66", "ASKHI": "47.5"}, {"data": "2012/11/02", "OPENPRC": "47.07", "PRC": "45.69", "BIDLO": "45.66", "ASKHI": "47.26"}, {"data": "2012/11/05", "OPENPRC": "45.63", "PRC": "45.35", "BIDLO": "45.19", "ASKHI": "46.05"}, {"data": "2012/11/06", "OPENPRC": "45.33", "PRC": "45.8", "BIDLO": "45.31", "ASKHI": "46.17"}, {"data": "2012/11/07", "OPENPRC": "45.47", "PRC": "45.24", "BIDLO": "44.81", "ASKHI": "45.59"}, {"data": "2012/11/08", "OPENPRC": "45.11", "PRC": "44.63", "BIDLO": "44.63", "ASKHI": "45.48"}, {"data": "2012/11/09", "OPENPRC": "44.37", "PRC": "44.92", "BIDLO": "44.17", "ASKHI": "45.33"}, {"data": "2012/11/12", "OPENPRC": "44.86", "PRC": "44.18", "BIDLO": "44.17", "ASKHI": "45.11"}, {"data": "2012/11/13", "OPENPRC": "43.95", "PRC": "44.52", "BIDLO": "43.83", "ASKHI": "45.0"}, {"data": "2012/11/14", "OPENPRC": "44.62", "PRC": "44.6", "BIDLO": "44.45", "ASKHI": "45.1031"}, {"data": "2012/11/15", "OPENPRC": "44.67", "PRC": "44.65", "BIDLO": "43.9392", "ASKHI": "44.83"}, {"data": "2012/11/16", "OPENPRC": "44.69", "PRC": "45.66", "BIDLO": "44.22", "ASKHI": "45.66"}, {"data": "2012/11/19", "OPENPRC": "45.96", "PRC": "45.9", "BIDLO": "45.74", "ASKHI": "46.25"}, {"data": "2012/11/20", "OPENPRC": "45.93", "PRC": "46.04", "BIDLO": "45.67", "ASKHI": "46.08"}, {"data": "2012/11/21", "OPENPRC": "46.2", "PRC": "46.0", "BIDLO": "45.64", "ASKHI": "46.28"}, {"data": "2012/11/23", "OPENPRC": "46.07", "PRC": "45.98", "BIDLO": "45.65", "ASKHI": "46.27"}, {"data": "2012/11/26", "OPENPRC": "45.85", "PRC": "45.93", "BIDLO": "45.76", "ASKHI": "46.49"}, {"data": "2012/11/27", "OPENPRC": "45.94", "PRC": "45.58", "BIDLO": "45.52", "ASKHI": "46.14"}, {"data": "2012/11/28", "OPENPRC": "45.3", "PRC": "44.88", "BIDLO": "44.22", "ASKHI": "45.3"}, {"data": "2012/11/29", "OPENPRC": "44.91", "PRC": "44.37", "BIDLO": "43.92", "ASKHI": "45.02"}, {"data": "2012/11/30", "OPENPRC": "44.4", "PRC": "44.87", "BIDLO": "44.15", "ASKHI": "44.98"}, {"data": "2012/12/03", "OPENPRC": "44.99", "PRC": "44.64", "BIDLO": "44.55", "ASKHI": "45.3434"}, {"data": "2012/12/04", "OPENPRC": "44.54", "PRC": "44.55", "BIDLO": "44.22", "ASKHI": "44.87"}, {"data": "2012/12/05", "OPENPRC": "44.58", "PRC": "44.41", "BIDLO": "43.92", "ASKHI": "44.73"}, {"data": "2012/12/06", "OPENPRC": "44.44", "PRC": "43.67", "BIDLO": "43.6", "ASKHI": "44.67"}, {"data": "2012/12/07", "OPENPRC": "43.69", "PRC": "43.0", "BIDLO": "42.76", "ASKHI": "43.99"}, {"data": "2012/12/10", "OPENPRC": "43.1", "PRC": "42.95", "BIDLO": "42.95", "ASKHI": "43.34"}, {"data": "2012/12/11", "OPENPRC": "43.0", "PRC": "43.69", "BIDLO": "43.0", "ASKHI": "43.84"}, {"data": "2012/12/12", "OPENPRC": "43.78", "PRC": "43.59", "BIDLO": "43.54", "ASKHI": "44.16"}, {"data": "2012/12/13", "OPENPRC": "43.58", "PRC": "43.17", "BIDLO": "42.98", "ASKHI": "43.87"}, {"data": "2012/12/14", "OPENPRC": "42.97", "PRC": "42.9", "BIDLO": "42.86", "ASKHI": "43.21"}, {"data": "2012/12/17", "OPENPRC": "42.96", "PRC": "43.72", "BIDLO": "42.96", "ASKHI": "43.74"}, {"data": "2012/12/18", "OPENPRC": "43.77", "PRC": "43.52", "BIDLO": "43.44", "ASKHI": "44.36"}, {"data": "2012/12/19", "OPENPRC": "43.63", "PRC": "43.45", "BIDLO": "43.36", "ASKHI": "44.0032"}, {"data": "2012/12/20", "OPENPRC": "43.46", "PRC": "43.85", "BIDLO": "43.23", "ASKHI": "43.94"}, {"data": "2012/12/21", "OPENPRC": "44.17", "PRC": "43.41", "BIDLO": "42.83", "ASKHI": "44.17"}, {"data": "2012/12/24", "OPENPRC": "43.3", "PRC": "43.24", "BIDLO": "43.0", "ASKHI": "43.432"}, {"data": "2012/12/26", "OPENPRC": "43.27", "PRC": "42.4", "BIDLO": "42.35", "ASKHI": "43.3"}, {"data": "2012/12/27", "OPENPRC": "42.35", "PRC": "42.16", "BIDLO": "41.69", "ASKHI": "42.63"}, {"data": "2012/12/28", "OPENPRC": "41.92", "PRC": "42.07", "BIDLO": "41.42", "ASKHI": "42.45"}, {"data": "2012/12/31", "OPENPRC": "41.94", "PRC": "42.75", "BIDLO": "41.82", "ASKHI": "42.82"}]